[
  {
    "coles": 205,
    "osm": "n11090786327",
    "x": -31.8775736,
    "y": 115.7776645
  },
  {
    "coles": 219,
    "osm": "n6267324359",
    "x": -12.4838279,
    "y": 130.9854249
  },
  {
    "coles": 256,
    "osm": "n1361288079",
    "x": -31.8953433,
    "y": 115.8711279
  },
  {
    "coles": 257,
    "osm": "n2470724940",
    "x": -32.5487322,
    "y": 115.7036291
  },
  {
    "coles": 260,
    "osm": "n11834411783",
    "x": -31.7055668,
    "y": 115.8011981
  },
  {
    "coles": 262,
    "osm": "n11834413687",
    "x": -31.8677455,
    "y": 115.9669194
  },
  {
    "coles": 263,
    "osm": "n11834417685",
    "x": -32.2199142,
    "y": 116.0068198
  },
  {
    "coles": 268,
    "osm": "w1014238723",
    "x": -33.6742411,
    "y": 115.2500777
  },
  {
    "coles": 270,
    "osm": "n5785330344",
    "x": -31.9438496,
    "y": 115.8228937
  },
  {
    "coles": 278,
    "osm": "n3846824556",
    "x": -31.8890555,
    "y": 116.0122292
  },
  {
    "coles": 282,
    "osm": "n10682977533",
    "x": -32.148061,
    "y": 115.9866245
  },
  {
    "coles": 285,
    "osm": "n5869781682",
    "x": -31.9349221,
    "y": 116.0048017
  },
  {
    "coles": 287,
    "osm": "n2201364948",
    "x": -32.3322023,
    "y": 115.814764
  },
  {
    "coles": 289,
    "osm": "n5490038607",
    "x": -31.7527835,
    "y": 115.8048485
  },
  {
    "coles": 290,
    "osm": "n8311537823",
    "x": -31.6496435,
    "y": 115.6973146
  },
  {
    "coles": 291,
    "osm": "n3094750074",
    "x": -33.6502003,
    "y": 115.3465701
  },
  {
    "coles": 292,
    "osm": "n600291937",
    "x": -31.9409408,
    "y": 115.833644
  },
  {
    "coles": 293,
    "osm": "n1447943194",
    "x": -32.6283824,
    "y": 115.8735886
  },
  {
    "coles": 294,
    "osm": "n1226177775",
    "x": -32.106008,
    "y": 115.938215
  },
  {
    "coles": 296,
    "osm": "w463590329",
    "x": -31.9810555,
    "y": 115.8625077
  },
  {
    "coles": 297,
    "osm": "n2669219781",
    "x": -33.6155277,
    "y": 115.1050136
  },
  {
    "coles": 298,
    "osm": "n11834415588",
    "x": -31.9016049,
    "y": 115.8003459
  },
  {
    "coles": 299,
    "osm": "n9465241471",
    "x": -31.9822551,
    "y": 115.7793881
  },
  {
    "coles": 302,
    "osm": "n5785372990",
    "x": -31.9372711,
    "y": 115.7929688
  },
  {
    "coles": 303,
    "osm": "n11834181804",
    "x": -31.831252,
    "y": 115.8029527
  },
  {
    "coles": 306,
    "osm": "n117191633",
    "x": -32.0691928,
    "y": 115.9500425
  },
  {
    "coles": 310,
    "osm": "n370543326",
    "x": -33.9515992,
    "y": 115.0731268
  },
  {
    "coles": 311,
    "osm": "w655517290",
    "x": -32.5351238,
    "y": 115.7437331
  },
  {
    "coles": 313,
    "osm": "n2395071641",
    "x": -20.7352953,
    "y": 116.8453677
  },
  {
    "coles": 314,
    "osm": "n4400693424",
    "x": -31.8711626,
    "y": 115.8627733
  },
  {
    "coles": 322,
    "osm": "n2206032459",
    "x": -32.0210508,
    "y": 115.9400081
  },
  {
    "coles": 324,
    "osm": "n247283901",
    "x": -17.9519049,
    "y": 122.2431404
  },
  {
    "coles": 325,
    "osm": "n1537571751",
    "x": -15.7756129,
    "y": 128.7398524
  },
  {
    "coles": 327,
    "osm": "n648365682",
    "x": -33.2799672,
    "y": 115.7158367
  },
  {
    "coles": 328,
    "osm": "n471432914",
    "x": -22.6942377,
    "y": 117.7958356
  },
  {
    "coles": 329,
    "osm": "n2100155735",
    "x": -32.3470702,
    "y": 115.7628321
  },
  {
    "coles": 330,
    "osm": "n567375048",
    "x": -31.9006681,
    "y": 116.1667639
  },
  {
    "coles": 332,
    "osm": "n9526576733",
    "x": -32.0340686,
    "y": 115.8342306
  },
  {
    "coles": 333,
    "osm": "n1143263494",
    "x": -32.1062755,
    "y": 115.8275641
  },
  {
    "coles": 334,
    "osm": "n1361315803",
    "x": -31.8966831,
    "y": 115.8988417
  },
  {
    "coles": 335,
    "osm": "n2509339459",
    "x": -31.7442395,
    "y": 115.7665936
  },
  {
    "coles": 336,
    "osm": "n3217078721",
    "x": -31.770053,
    "y": 115.7651747
  },
  {
    "coles": 337,
    "osm": "n8926779305",
    "x": -32.0529588,
    "y": 115.9788575
  },
  {
    "coles": 338,
    "osm": "n9481789274",
    "x": -31.844616,
    "y": 115.8102813
  },
  {
    "coles": 339,
    "osm": "n691502076",
    "x": -33.3256208,
    "y": 115.6402745
  },
  {
    "coles": 340,
    "osm": "n6152746378",
    "x": -31.9848534,
    "y": 115.9007146
  },
  {
    "coles": 343,
    "osm": "n8926800466",
    "x": -32.1525298,
    "y": 116.0157135
  },
  {
    "coles": 344,
    "osm": "n11834167628",
    "x": -31.8769266,
    "y": 115.8961439
  },
  {
    "coles": 345,
    "osm": "n8929772133",
    "x": -32.1125237,
    "y": 116.0147812
  },
  {
    "coles": 347,
    "osm": "w1150051053",
    "x": -31.909721,
    "y": 115.8486653
  },
  {
    "coles": 348,
    "osm": "n11834093840",
    "x": -32.5614132,
    "y": 115.6886714
  },
  {
    "coles": 350,
    "osm": "n33682726",
    "x": -28.7674325,
    "y": 114.6171268
  },
  {
    "coles": 352,
    "osm": "n9739204034",
    "x": -32.033956,
    "y": 115.7912758
  },
  {
    "coles": 353,
    "osm": "w835224336",
    "x": -31.9874328,
    "y": 116.0101477
  },
  {
    "coles": 356,
    "osm": "n454837973",
    "x": -32.0105446,
    "y": 115.8864897
  },
  {
    "coles": 357,
    "osm": "n4393253275",
    "x": -31.9322152,
    "y": 115.8584308
  },
  {
    "coles": 358,
    "osm": "n2216225139",
    "x": -32.0583869,
    "y": 115.8802194
  },
  {
    "coles": 362,
    "osm": "n11834188176",
    "x": -32.4926529,
    "y": 115.7483645
  },
  {
    "coles": 363,
    "osm": "n11834095403",
    "x": -31.8765744,
    "y": 115.9259113
  },
  {
    "coles": 364,
    "osm": "n1681468901",
    "x": -35.0198682,
    "y": 117.8824345
  },
  {
    "coles": 365,
    "osm": "n11834275550",
    "x": -31.8299267,
    "y": 115.8542105
  },
  {
    "coles": 370,
    "osm": "n1960888133",
    "x": -32.2905521,
    "y": 115.7422694
  },
  {
    "coles": 371,
    "osm": "n11806194535",
    "x": -31.8094455,
    "y": 115.7433867
  },
  {
    "coles": 375,
    "osm": "n628498696",
    "x": -31.690367,
    "y": 115.717247
  },
  {
    "coles": 378,
    "osm": "n4589261070",
    "x": -31.87312,
    "y": 115.8297914
  },
  {
    "coles": 379,
    "osm": "n1973347834",
    "x": -31.9297804,
    "y": 115.8976296
  },
  {
    "coles": 380,
    "osm": "n370584885",
    "x": -31.8952171,
    "y": 115.7573181
  },
  {
    "coles": 381,
    "osm": "n8926841153",
    "x": -32.1316827,
    "y": 116.0011742
  },
  {
    "coles": 383,
    "osm": "w145169229",
    "x": -31.9164847,
    "y": 115.8903161
  },
  {
    "coles": 384,
    "osm": "w553155802",
    "x": -32.0686397,
    "y": 116.0004157
  },
  {
    "coles": 385,
    "osm": "n2459085753",
    "x": -20.4106645,
    "y": 118.6005731
  },
  {
    "coles": 388,
    "osm": "n3094715834",
    "x": -34.2421388,
    "y": 116.14423
  },
  {
    "coles": 390,
    "osm": "n11806192946",
    "x": -33.3576899,
    "y": 116.1524896
  },
  {
    "coles": 391,
    "osm": "n2953883893",
    "x": -32.067564,
    "y": 115.8157926
  },
  {
    "coles": 392,
    "osm": "n4646407492",
    "x": -32.008655,
    "y": 115.7612049
  },
  {
    "coles": 394,
    "osm": "n270862126",
    "x": -31.9728148,
    "y": 116.0594191
  },
  {
    "coles": 395,
    "osm": "n11834430075",
    "x": -31.9028304,
    "y": 115.953361
  },
  {
    "coles": 396,
    "osm": "n739450193",
    "x": -32.9324977,
    "y": 117.1770218
  },
  {
    "coles": 398,
    "osm": "n11834184542",
    "x": -31.8886649,
    "y": 116.0470939
  },
  {
    "coles": 399,
    "osm": "n691538034",
    "x": -33.3597468,
    "y": 115.6459554
  },
  {
    "coles": 401,
    "osm": "n3490412523",
    "x": -34.9047153,
    "y": 138.6556898
  },
  {
    "coles": 403,
    "osm": "n497197520",
    "x": -34.9048091,
    "y": 138.5318295
  },
  {
    "coles": 404,
    "osm": "w1250385871",
    "x": -12.3765119,
    "y": 130.8812594
  },
  {
    "coles": 406,
    "osm": "n93943553",
    "x": -34.9558059,
    "y": 138.5656154
  },
  {
    "coles": 408,
    "osm": "n7877858285",
    "x": -34.8622006,
    "y": 138.682929
  },
  {
    "coles": 414,
    "osm": "n854633067",
    "x": -34.8216013,
    "y": 138.7181094
  },
  {
    "coles": 418,
    "osm": "n2364190854",
    "x": -23.6983785,
    "y": 133.8790594
  },
  {
    "coles": 419,
    "osm": "n10943132300",
    "x": -34.9942667,
    "y": 138.5558233
  },
  {
    "coles": 420,
    "osm": "w483181333",
    "x": -34.9793381,
    "y": 138.5155069
  },
  {
    "coles": 423,
    "osm": "n890985997",
    "x": -34.8297043,
    "y": 138.6485013
  },
  {
    "coles": 429,
    "osm": "n9362948334",
    "x": -34.8969548,
    "y": 138.5575324
  },
  {
    "coles": 430,
    "osm": "n762177762",
    "x": -34.9512718,
    "y": 138.6067901
  },
  {
    "coles": 436,
    "osm": "n5330994352",
    "x": -35.1071303,
    "y": 138.5207201
  },
  {
    "coles": 437,
    "osm": "n3200715069",
    "x": -35.1417175,
    "y": 138.4953971
  },
  {
    "coles": 439,
    "osm": "n1239467019",
    "x": -34.7679842,
    "y": 138.6240503
  },
  {
    "coles": 440,
    "osm": "w295319198",
    "x": -34.7226433,
    "y": 135.8613462
  },
  {
    "coles": 442,
    "osm": "n7344923140",
    "x": -33.1909404,
    "y": 138.0075933
  },
  {
    "coles": 444,
    "osm": "n1404335340",
    "x": -34.5952595,
    "y": 138.7483921
  },
  {
    "coles": 445,
    "osm": "w132181982",
    "x": -35.0088693,
    "y": 138.7602038
  },
  {
    "coles": 446,
    "osm": "n11834282070",
    "x": -34.8859206,
    "y": 138.6907907
  },
  {
    "coles": 447,
    "osm": "n310536027",
    "x": -35.01871,
    "y": 138.6157937
  },
  {
    "coles": 448,
    "osm": "n2037714286",
    "x": -34.9104686,
    "y": 138.6293555
  },
  {
    "coles": 450,
    "osm": "n467703425",
    "x": -12.4815653,
    "y": 130.9849839
  },
  {
    "coles": 451,
    "osm": "n2307374386",
    "x": -34.2807978,
    "y": 140.6090503
  },
  {
    "coles": 452,
    "osm": "n11834184811",
    "x": -34.9825287,
    "y": 138.5724363
  },
  {
    "coles": 453,
    "osm": "n512275360",
    "x": -34.9420645,
    "y": 138.6412932
  },
  {
    "coles": 455,
    "osm": "w203684561",
    "x": -34.8811731,
    "y": 138.4914867
  },
  {
    "coles": 456,
    "osm": "n7989899085",
    "x": -32.492507,
    "y": 137.763812
  },
  {
    "coles": 458,
    "osm": "n2179459957",
    "x": -35.0174397,
    "y": 138.5445305
  },
  {
    "coles": 459,
    "osm": "n4316700686",
    "x": -34.8306405,
    "y": 138.6935739
  },
  {
    "coles": 460,
    "osm": "n2478924751",
    "x": -12.4637037,
    "y": 130.8395775
  },
  {
    "coles": 461,
    "osm": "w226833782",
    "x": -34.8848724,
    "y": 138.5935287
  },
  {
    "coles": 462,
    "osm": "n859918539",
    "x": -34.7175698,
    "y": 138.6676306
  },
  {
    "coles": 465,
    "osm": "w441742677",
    "x": -32.0394312,
    "y": 115.9076519
  },
  {
    "coles": 471,
    "osm": "n848338230",
    "x": -34.8752494,
    "y": 138.6016148
  },
  {
    "coles": 472,
    "osm": "n493314043",
    "x": -12.3959003,
    "y": 130.8952414
  },
  {
    "coles": 478,
    "osm": "n6976693902",
    "x": -34.993574,
    "y": 117.8555655
  },
  {
    "coles": 481,
    "osm": "n4308785593",
    "x": -31.9513993,
    "y": 115.8573763
  },
  {
    "coles": 485,
    "osm": "n1473222548",
    "x": -31.781925,
    "y": 115.970274
  },
  {
    "coles": 486,
    "osm": "n5441578754",
    "x": -12.5206589,
    "y": 131.0415168
  },
  {
    "coles": 488,
    "osm": "n11826874479",
    "x": -32.2454841,
    "y": 115.8138877
  },
  {
    "coles": 489,
    "osm": "n11806194534",
    "x": -31.7971194,
    "y": 115.7502799
  },
  {
    "coles": 490,
    "osm": "n1143293760",
    "x": -32.1319974,
    "y": 115.8565183
  },
  {
    "coles": 492,
    "osm": "n3925399930",
    "x": -31.6579613,
    "y": 116.6700452
  },
  {
    "coles": 493,
    "osm": "n3932997855",
    "x": -33.3189212,
    "y": 115.7175548
  },
  {
    "coles": 494,
    "osm": "n11834192916",
    "x": -32.1280906,
    "y": 115.7980553
  },
  {
    "coles": 499,
    "osm": "n467178200",
    "x": -34.8489615,
    "y": 138.504526
  },
  {
    "coles": 501,
    "osm": "w875654863",
    "x": -38.1701863,
    "y": 144.3487229
  },
  {
    "coles": 504,
    "osm": "n583067216",
    "x": -37.8915244,
    "y": 145.14381
  },
  {
    "coles": 506,
    "osm": "n3345300340",
    "x": -37.6735307,
    "y": 145.159387
  },
  {
    "coles": 507,
    "osm": "n964641320",
    "x": -37.8458418,
    "y": 145.0452563
  },
  {
    "coles": 508,
    "osm": "n319602021",
    "x": -37.8768747,
    "y": 145.1645918
  },
  {
    "coles": 510,
    "osm": "n9630439544",
    "x": -37.7710664,
    "y": 145.2940313
  },
  {
    "coles": 511,
    "osm": "n1311737974",
    "x": -38.0759456,
    "y": 144.3556949
  },
  {
    "coles": 512,
    "osm": "n4935336424",
    "x": -37.8319294,
    "y": 144.9609368
  },
  {
    "coles": 514,
    "osm": "n846426635",
    "x": -37.7652693,
    "y": 145.0918512
  },
  {
    "coles": 516,
    "osm": "n461534089",
    "x": -37.8952497,
    "y": 144.7530363
  },
  {
    "coles": 519,
    "osm": "n325276531",
    "x": -37.6856825,
    "y": 144.5657612
  },
  {
    "coles": 520,
    "osm": "w326037694",
    "x": -38.0633305,
    "y": 145.455558
  },
  {
    "coles": 522,
    "osm": "w826855625",
    "x": -37.8200237,
    "y": 145.0354691
  },
  {
    "coles": 523,
    "osm": "w262518576",
    "x": -37.7674337,
    "y": 144.863378
  },
  {
    "coles": 524,
    "osm": "n2045666746",
    "x": -37.7612778,
    "y": 145.1698916
  },
  {
    "coles": 526,
    "osm": "w145887879",
    "x": -37.8152905,
    "y": 145.1927791
  },
  {
    "coles": 527,
    "osm": "n3338903502",
    "x": -37.849012,
    "y": 144.7037194
  },
  {
    "coles": 528,
    "osm": "w90625912",
    "x": -37.8836877,
    "y": 145.2753114
  },
  {
    "coles": 530,
    "osm": "w53843626",
    "x": -37.86892,
    "y": 144.8299879
  },
  {
    "coles": 531,
    "osm": "n1500755604",
    "x": -38.0686223,
    "y": 145.144883
  },
  {
    "coles": 536,
    "osm": "n1583422493",
    "x": -37.9280896,
    "y": 145.1181472
  },
  {
    "coles": 537,
    "osm": "n2163569101",
    "x": -37.8825051,
    "y": 144.7346373
  },
  {
    "coles": 538,
    "osm": "w266497009",
    "x": -38.1856035,
    "y": 144.4539461
  },
  {
    "coles": 540,
    "osm": "n1169919216",
    "x": -37.9048141,
    "y": 145.1622732
  },
  {
    "coles": 541,
    "osm": "n1266906766",
    "x": -38.3515418,
    "y": 144.9227978
  },
  {
    "coles": 542,
    "osm": "n836083881",
    "x": -37.8576259,
    "y": 144.8974163
  },
  {
    "coles": 544,
    "osm": "n981973114",
    "x": -38.061441,
    "y": 145.3397959
  },
  {
    "coles": 545,
    "osm": "w112553029",
    "x": -37.7557097,
    "y": 145.0693397
  },
  {
    "coles": 546,
    "osm": "w39581680",
    "x": -37.9840734,
    "y": 145.0643704
  },
  {
    "coles": 547,
    "osm": "n515973782",
    "x": -38.1620606,
    "y": 145.9324454
  },
  {
    "coles": 548,
    "osm": "w165670177",
    "x": -37.8251379,
    "y": 147.6327063
  },
  {
    "coles": 549,
    "osm": "n1530420284",
    "x": -37.9654121,
    "y": 145.1730576
  },
  {
    "coles": 550,
    "osm": "n2391873439",
    "x": -37.6889515,
    "y": 144.9599995
  },
  {
    "coles": 552,
    "osm": "w142234405",
    "x": -37.2874316,
    "y": 144.9480741
  },
  {
    "coles": 553,
    "osm": "n960805700",
    "x": -37.9357915,
    "y": 145.1905999
  },
  {
    "coles": 554,
    "osm": "n1278129196",
    "x": -37.7323759,
    "y": 144.7425236
  },
  {
    "coles": 556,
    "osm": "n1271728963",
    "x": -37.8757512,
    "y": 144.6145175
  },
  {
    "coles": 558,
    "osm": "n1969747367",
    "x": -37.7587406,
    "y": 144.7901048
  },
  {
    "coles": 559,
    "osm": "n667225621",
    "x": -37.8147983,
    "y": 144.9518038
  },
  {
    "coles": 560,
    "osm": "n1428952005",
    "x": -37.8291542,
    "y": 145.0563202
  },
  {
    "coles": 561,
    "osm": "n1808687856",
    "x": -38.2390054,
    "y": 146.3983912
  },
  {
    "coles": 562,
    "osm": "w108219853",
    "x": -37.3421575,
    "y": 144.1417141
  },
  {
    "coles": 563,
    "osm": "n3545924632",
    "x": -38.3811893,
    "y": 142.5207433
  },
  {
    "coles": 565,
    "osm": "w25797855",
    "x": -37.7930208,
    "y": 145.0647489
  },
  {
    "coles": 569,
    "osm": "n2172299040",
    "x": -37.679686,
    "y": 144.9186507
  },
  {
    "coles": 570,
    "osm": "w1105684358",
    "x": -37.7849101,
    "y": 145.3153865
  },
  {
    "coles": 571,
    "osm": "n932432768",
    "x": -37.8679128,
    "y": 144.9919849
  },
  {
    "coles": 573,
    "osm": "n3418300526",
    "x": -37.8479845,
    "y": 144.9937651
  },
  {
    "coles": 574,
    "osm": "w264714416",
    "x": -35.3404775,
    "y": 143.5574889
  },
  {
    "coles": 575,
    "osm": "w166249327",
    "x": -37.8604328,
    "y": 145.0291228
  },
  {
    "coles": 581,
    "osm": "n1583422492",
    "x": -37.9259993,
    "y": 145.1185924
  },
  {
    "coles": 582,
    "osm": "n636217129",
    "x": -37.7272917,
    "y": 144.895358
  },
  {
    "coles": 583,
    "osm": "w53839901",
    "x": -37.7978511,
    "y": 144.9779798
  },
  {
    "coles": 584,
    "osm": "n314087330",
    "x": -37.8535375,
    "y": 145.1487011
  },
  {
    "coles": 585,
    "osm": "n566528267",
    "x": -37.682907,
    "y": 145.0704091
  },
  {
    "coles": 591,
    "osm": "n368387447",
    "x": -38.2240036,
    "y": 145.1703702
  },
  {
    "coles": 592,
    "osm": "n2502841974",
    "x": -37.7424437,
    "y": 144.9658474
  },
  {
    "coles": 594,
    "osm": "w295344976",
    "x": -34.1833877,
    "y": 142.159892
  },
  {
    "coles": 595,
    "osm": "w38225804",
    "x": -37.9175523,
    "y": 145.0385071
  },
  {
    "coles": 597,
    "osm": "w112564353",
    "x": -37.7681531,
    "y": 145.0418563
  },
  {
    "coles": 599,
    "osm": "w382367751",
    "x": -37.7145141,
    "y": 145.0073125
  },
  {
    "coles": 601,
    "osm": "n335617280",
    "x": -37.8612829,
    "y": 145.2875436
  },
  {
    "coles": 602,
    "osm": "n6634574085",
    "x": -37.8099061,
    "y": 144.963719
  },
  {
    "coles": 603,
    "osm": "n364658541",
    "x": -38.0857063,
    "y": 145.4709464
  },
  {
    "coles": 604,
    "osm": "n5222791629",
    "x": -37.6730186,
    "y": 145.0169622
  },
  {
    "coles": 606,
    "osm": "n2047923121",
    "x": -37.4851623,
    "y": 144.5906378
  },
  {
    "coles": 608,
    "osm": "n3624193295",
    "x": -37.639343,
    "y": 144.8825125
  },
  {
    "coles": 609,
    "osm": "n218028470",
    "x": -37.7914336,
    "y": 145.1718422
  },
  {
    "coles": 613,
    "osm": "n2254087485",
    "x": -37.7837126,
    "y": 144.7711213
  },
  {
    "coles": 615,
    "osm": "w112560824",
    "x": -36.7139538,
    "y": 142.1977247
  },
  {
    "coles": 616,
    "osm": "n655118709",
    "x": -37.5349147,
    "y": 143.8242493
  },
  {
    "coles": 617,
    "osm": "n2315713089",
    "x": -36.0496837,
    "y": 146.9328791
  },
  {
    "coles": 618,
    "osm": "w490242047",
    "x": -37.8282395,
    "y": 144.8480047
  },
  {
    "coles": 620,
    "osm": "w113338781",
    "x": -36.131069,
    "y": 144.7494176
  },
  {
    "coles": 621,
    "osm": "n1301802142",
    "x": -38.1030621,
    "y": 145.2652502
  },
  {
    "coles": 622,
    "osm": "n2177939910",
    "x": -37.7569568,
    "y": 145.3133008
  },
  {
    "coles": 625,
    "osm": "n427864933",
    "x": -37.9922837,
    "y": 145.1719538
  },
  {
    "coles": 626,
    "osm": "w93168907",
    "x": -38.1736171,
    "y": 146.2588285
  },
  {
    "coles": 627,
    "osm": "n939020309",
    "x": -37.7673811,
    "y": 145.0017674
  },
  {
    "coles": 628,
    "osm": "w109937964",
    "x": -37.563876,
    "y": 143.8631904
  },
  {
    "coles": 629,
    "osm": "w103961488",
    "x": -38.1343612,
    "y": 145.8558201
  },
  {
    "coles": 630,
    "osm": "n278926518",
    "x": -37.794199,
    "y": 145.2791738
  },
  {
    "coles": 631,
    "osm": "n666846439",
    "x": -37.7758523,
    "y": 144.9626265
  },
  {
    "coles": 636,
    "osm": "n2491846390",
    "x": -36.1211495,
    "y": 146.881416
  },
  {
    "coles": 637,
    "osm": "n565827592",
    "x": -37.8155086,
    "y": 145.2212725
  },
  {
    "coles": 638,
    "osm": "w51469747",
    "x": -36.7612667,
    "y": 144.282664
  },
  {
    "coles": 639,
    "osm": "w124007107",
    "x": -37.7052372,
    "y": 144.9167744
  },
  {
    "coles": 640,
    "osm": "w51968747",
    "x": -38.306299,
    "y": 145.1914173
  },
  {
    "coles": 641,
    "osm": "n317697330",
    "x": -37.949435,
    "y": 145.0033564
  },
  {
    "coles": 643,
    "osm": "n280897051",
    "x": -37.8855399,
    "y": 145.0845484
  },
  {
    "coles": 645,
    "osm": "n1281493538",
    "x": -37.901233,
    "y": 145.0903717
  },
  {
    "coles": 646,
    "osm": "n11834288794",
    "x": -37.8386433,
    "y": 144.9417288
  },
  {
    "coles": 647,
    "osm": "n260710477",
    "x": -37.83496,
    "y": 145.1643348
  },
  {
    "coles": 648,
    "osm": "n1347450503",
    "x": -37.5781965,
    "y": 144.7293169
  },
  {
    "coles": 649,
    "osm": "n1505820163",
    "x": -37.7273876,
    "y": 144.8065418
  },
  {
    "coles": 650,
    "osm": "n260559651",
    "x": -37.8682575,
    "y": 145.240404
  },
  {
    "coles": 651,
    "osm": "n1557920937",
    "x": -37.9775716,
    "y": 145.2583643
  },
  {
    "coles": 652,
    "osm": "n365210773",
    "x": -38.1421829,
    "y": 145.1234117
  },
  {
    "coles": 654,
    "osm": "n915085888",
    "x": -37.6543378,
    "y": 145.0188275
  },
  {
    "coles": 656,
    "osm": "n747047587",
    "x": -37.913326,
    "y": 144.9927645
  },
  {
    "coles": 657,
    "osm": "n538206163",
    "x": -37.7025681,
    "y": 145.1029553
  },
  {
    "coles": 658,
    "osm": "n1364005492",
    "x": -36.1283141,
    "y": 146.8641891
  },
  {
    "coles": 660,
    "osm": "n616513028",
    "x": -37.9865785,
    "y": 145.2183528
  },
  {
    "coles": 662,
    "osm": "n2153947797",
    "x": -37.7563965,
    "y": 145.3542278
  },
  {
    "coles": 663,
    "osm": "n1918505758",
    "x": -37.8732777,
    "y": 144.7759322
  },
  {
    "coles": 665,
    "osm": "n1274284215",
    "x": -38.267528,
    "y": 144.5238339
  },
  {
    "coles": 667,
    "osm": "n1080087948",
    "x": -37.7645234,
    "y": 144.9219203
  },
  {
    "coles": 668,
    "osm": "n570758511",
    "x": -37.8685845,
    "y": 144.9806027
  },
  {
    "coles": 669,
    "osm": "n365211575",
    "x": -37.9589132,
    "y": 145.0512356
  },
  {
    "coles": 670,
    "osm": "w897346810",
    "x": -38.1512148,
    "y": 145.196592
  },
  {
    "coles": 671,
    "osm": "n591382457",
    "x": -37.8175611,
    "y": 144.9649673
  },
  {
    "coles": 672,
    "osm": "n1315813958",
    "x": -37.6751442,
    "y": 144.4402008
  },
  {
    "coles": 673,
    "osm": "n367127064",
    "x": -38.2193814,
    "y": 145.0401252
  },
  {
    "coles": 674,
    "osm": "n360214093",
    "x": -38.0778107,
    "y": 145.4790259
  },
  {
    "coles": 675,
    "osm": "n11209192330",
    "x": -35.5313637,
    "y": 144.9553528
  },
  {
    "coles": 677,
    "osm": "n258471456",
    "x": -37.8547864,
    "y": 145.1826504
  },
  {
    "coles": 678,
    "osm": "n531399027",
    "x": -37.7151557,
    "y": 145.1486437
  },
  {
    "coles": 679,
    "osm": "n1220951682",
    "x": -38.1069769,
    "y": 147.0644793
  },
  {
    "coles": 680,
    "osm": "n660942564",
    "x": -37.6524334,
    "y": 145.5181925
  },
  {
    "coles": 681,
    "osm": "n2020888947",
    "x": -37.9347488,
    "y": 145.1568383
  },
  {
    "coles": 682,
    "osm": "n2918617899",
    "x": -37.6972847,
    "y": 145.0579698
  },
  {
    "coles": 684,
    "osm": "n369690027",
    "x": -37.9828511,
    "y": 145.2136939
  },
  {
    "coles": 685,
    "osm": "n492900388",
    "x": -37.6508313,
    "y": 145.0687423
  },
  {
    "coles": 686,
    "osm": "w112445024",
    "x": -37.8139592,
    "y": 145.0115685
  },
  {
    "coles": 688,
    "osm": "n612554194",
    "x": -36.3599515,
    "y": 146.3172286
  },
  {
    "coles": 691,
    "osm": "n290313333",
    "x": -37.8747789,
    "y": 144.6794291
  },
  {
    "coles": 693,
    "osm": "n3003966268",
    "x": -36.0814428,
    "y": 146.9135818
  },
  {
    "coles": 694,
    "osm": "n1222247271",
    "x": -38.1939842,
    "y": 146.5398932
  },
  {
    "coles": 695,
    "osm": "w894009103",
    "x": -36.3828779,
    "y": 145.4008624
  },
  {
    "coles": 696,
    "osm": "n278111955",
    "x": -38.3614651,
    "y": 144.8921554
  },
  {
    "coles": 697,
    "osm": "n280708140",
    "x": -37.9208945,
    "y": 145.2375525
  },
  {
    "coles": 699,
    "osm": "n1760404273",
    "x": -38.0522568,
    "y": 145.2568486
  },
  {
    "coles": 702,
    "osm": "n537535100",
    "x": -33.7182332,
    "y": 150.9202652
  },
  {
    "coles": 703,
    "osm": "n601280579",
    "x": -36.2356585,
    "y": 149.1264377
  },
  {
    "coles": 704,
    "osm": "n11834180913",
    "x": -35.1136679,
    "y": 147.3705424
  },
  {
    "coles": 706,
    "osm": "n11834301371",
    "x": -33.8360618,
    "y": 151.0845422
  },
  {
    "coles": 709,
    "osm": "n267673904",
    "x": -33.6712368,
    "y": 150.6080029
  },
  {
    "coles": 710,
    "osm": "n20827870",
    "x": -33.8770719,
    "y": 151.2071568
  },
  {
    "coles": 711,
    "osm": "n2640571385",
    "x": -34.1687013,
    "y": 150.6136503
  },
  {
    "coles": 713,
    "osm": "n4417577184",
    "x": -34.0282621,
    "y": 150.7339588
  },
  {
    "coles": 716,
    "osm": "n8150855355",
    "x": -34.4356756,
    "y": 150.8629466
  },
  {
    "coles": 717,
    "osm": "n248180844",
    "x": -33.7326235,
    "y": 151.1273443
  },
  {
    "coles": 720,
    "osm": "n2690125720",
    "x": -33.9343534,
    "y": 151.0690979
  },
  {
    "coles": 723,
    "osm": "n1286302021",
    "x": -33.9194401,
    "y": 150.9246498
  },
  {
    "coles": 725,
    "osm": "n1923647661",
    "x": -35.1374445,
    "y": 147.3322641
  },
  {
    "coles": 726,
    "osm": "n3141239293",
    "x": -33.7661197,
    "y": 150.8210589
  },
  {
    "coles": 728,
    "osm": "n2445268314",
    "x": -33.869488,
    "y": 151.1963751
  },
  {
    "coles": 735,
    "osm": "w205290012",
    "x": -35.325637,
    "y": 149.082357
  },
  {
    "coles": 737,
    "osm": "n4655090289",
    "x": -33.9413484,
    "y": 151.238906
  },
  {
    "coles": 739,
    "osm": "w238843788",
    "x": -36.6750823,
    "y": 149.8451997
  },
  {
    "coles": 745,
    "osm": "w172393148",
    "x": -33.7851655,
    "y": 151.2687502
  },
  {
    "coles": 746,
    "osm": "n470367343",
    "x": -32.9077062,
    "y": 151.7257102
  },
  {
    "coles": 748,
    "osm": "n441178926",
    "x": -35.2527359,
    "y": 149.0713136
  },
  {
    "coles": 750,
    "osm": "w778206509",
    "x": -33.9260637,
    "y": 151.1245724
  },
  {
    "coles": 752,
    "osm": "n6364686440",
    "x": -33.3079881,
    "y": 151.4099597
  },
  {
    "coles": 754,
    "osm": "n2073247385",
    "x": -33.8750628,
    "y": 151.2224263
  },
  {
    "coles": 757,
    "osm": "n2381945007",
    "x": -35.300554,
    "y": 148.2214725
  },
  {
    "coles": 760,
    "osm": "w23707239",
    "x": -33.6881581,
    "y": 151.1066579
  },
  {
    "coles": 761,
    "osm": "w324081716",
    "x": -33.7467187,
    "y": 151.0502221
  },
  {
    "coles": 762,
    "osm": "n792213520",
    "x": -33.9861952,
    "y": 151.1468869
  },
  {
    "coles": 766,
    "osm": "n5686459525",
    "x": -34.0345703,
    "y": 151.1028151
  },
  {
    "coles": 768,
    "osm": "w173897520",
    "x": -33.7719776,
    "y": 151.0799947
  },
  {
    "coles": 770,
    "osm": "n4450003390",
    "x": -33.8655396,
    "y": 151.2778593
  },
  {
    "coles": 772,
    "osm": "n11823898099",
    "x": -34.0099239,
    "y": 151.1035857
  },
  {
    "coles": 778,
    "osm": "n1894436130",
    "x": -34.4941172,
    "y": 150.7955353
  },
  {
    "coles": 779,
    "osm": "n1326569197",
    "x": -35.2378963,
    "y": 149.0647435
  },
  {
    "coles": 780,
    "osm": "w435253538",
    "x": -34.8739618,
    "y": 150.6036211
  },
  {
    "coles": 781,
    "osm": "w618555487",
    "x": -33.2648843,
    "y": 151.5390692
  },
  {
    "coles": 782,
    "osm": "n1081257981",
    "x": -33.9665259,
    "y": 151.1051259
  },
  {
    "coles": 783,
    "osm": "n6444376904",
    "x": -34.0178858,
    "y": 151.0805261
  },
  {
    "coles": 784,
    "osm": "w392196354",
    "x": -33.7521541,
    "y": 151.2895962
  },
  {
    "coles": 785,
    "osm": "w55951439",
    "x": -34.0571349,
    "y": 150.6936141
  },
  {
    "coles": 786,
    "osm": "n623810974",
    "x": -33.40486,
    "y": 151.3513842
  },
  {
    "coles": 788,
    "osm": "n2455161608",
    "x": -32.2502565,
    "y": 148.6000522
  },
  {
    "coles": 791,
    "osm": "n201642843",
    "x": -33.8900655,
    "y": 151.1248645
  },
  {
    "coles": 792,
    "osm": "n3296509023",
    "x": -33.5955212,
    "y": 150.7494905
  },
  {
    "coles": 793,
    "osm": "w155003734",
    "x": -34.0648856,
    "y": 151.0111708
  },
  {
    "coles": 796,
    "osm": "n3143491295",
    "x": -33.7433082,
    "y": 150.9233881
  },
  {
    "coles": 797,
    "osm": "n2267893633",
    "x": -33.6964885,
    "y": 151.2949301
  },
  {
    "coles": 798,
    "osm": "n5895209485",
    "x": -33.3454432,
    "y": 151.4961917
  },
  {
    "coles": 800,
    "osm": "w584900508",
    "x": -33.916242,
    "y": 151.2398779
  },
  {
    "coles": 801,
    "osm": "n2499039583",
    "x": -33.4861499,
    "y": 150.1537648
  },
  {
    "coles": 802,
    "osm": "n1277752751",
    "x": -34.7522907,
    "y": 149.7209836
  },
  {
    "coles": 803,
    "osm": "n596068074",
    "x": -35.1862687,
    "y": 149.1359771
  },
  {
    "coles": 804,
    "osm": "w35832271",
    "x": -34.479945,
    "y": 150.4194816
  },
  {
    "coles": 807,
    "osm": "w139184580",
    "x": -33.0913082,
    "y": 151.6373774
  },
  {
    "coles": 809,
    "osm": "n4956462389",
    "x": -33.8930298,
    "y": 151.2482325
  },
  {
    "coles": 811,
    "osm": "n3287366428",
    "x": -35.7073396,
    "y": 150.1755671
  },
  {
    "coles": 813,
    "osm": "n489520185",
    "x": -32.9379729,
    "y": 151.7581818
  },
  {
    "coles": 814,
    "osm": "n6325242052",
    "x": -33.6539986,
    "y": 151.3213907
  },
  {
    "coles": 815,
    "osm": "n4742485532",
    "x": -33.7989581,
    "y": 151.2852807
  },
  {
    "coles": 819,
    "osm": "n3084114969",
    "x": -33.2412704,
    "y": 151.5046423
  },
  {
    "coles": 820,
    "osm": "n340288607",
    "x": -35.351761,
    "y": 149.2356033
  },
  {
    "coles": 821,
    "osm": "n552841784",
    "x": -33.428425,
    "y": 151.3159551
  },
  {
    "coles": 822,
    "osm": "n3236911130",
    "x": -34.4862559,
    "y": 150.8885311
  },
  {
    "coles": 823,
    "osm": "n3582317993",
    "x": -33.0343818,
    "y": 151.6588263
  },
  {
    "coles": 824,
    "osm": "n413460738",
    "x": -32.9028057,
    "y": 151.6678557
  },
  {
    "coles": 825,
    "osm": "n836020462",
    "x": -33.7300036,
    "y": 151.0057637
  },
  {
    "coles": 827,
    "osm": "n2434575170",
    "x": -33.7489665,
    "y": 150.879534
  },
  {
    "coles": 829,
    "osm": "n1916708985",
    "x": -33.8296546,
    "y": 151.2186431
  },
  {
    "coles": 831,
    "osm": "n768580567",
    "x": -33.9594429,
    "y": 151.15442
  },
  {
    "coles": 832,
    "osm": "n3910347158",
    "x": -33.8313696,
    "y": 151.1279539
  },
  {
    "coles": 833,
    "osm": "w496416256",
    "x": -32.9421143,
    "y": 151.7109729
  },
  {
    "coles": 834,
    "osm": "n3937568230",
    "x": -33.9069731,
    "y": 150.8678055
  },
  {
    "coles": 835,
    "osm": "n6067912167",
    "x": -33.2826679,
    "y": 149.0998301
  },
  {
    "coles": 836,
    "osm": "n364050600",
    "x": -33.4158641,
    "y": 149.581628
  },
  {
    "coles": 838,
    "osm": "n3897655338",
    "x": -34.2911145,
    "y": 146.0547821
  },
  {
    "coles": 839,
    "osm": "n3610075758",
    "x": -33.8838408,
    "y": 151.1932625
  },
  {
    "coles": 840,
    "osm": "n1343250217",
    "x": -33.8656811,
    "y": 151.2062069
  },
  {
    "coles": 842,
    "osm": "n6817258319",
    "x": -33.9548008,
    "y": 150.9440374
  },
  {
    "coles": 843,
    "osm": "n3737447690",
    "x": -33.7728999,
    "y": 150.971111
  },
  {
    "coles": 844,
    "osm": "n1080476559",
    "x": -33.6070776,
    "y": 150.818948
  },
  {
    "coles": 845,
    "osm": "n637944169",
    "x": -35.3583008,
    "y": 150.4721888
  },
  {
    "coles": 846,
    "osm": "n1899876558",
    "x": -33.8863247,
    "y": 151.1582955
  },
  {
    "coles": 847,
    "osm": "n3007866611",
    "x": -33.9968174,
    "y": 151.0422476
  },
  {
    "coles": 848,
    "osm": "n458724979",
    "x": -35.3467501,
    "y": 149.0855942
  },
  {
    "coles": 849,
    "osm": "n9610209441",
    "x": -33.8561794,
    "y": 151.1626686
  },
  {
    "coles": 850,
    "osm": "n2063892295",
    "x": -33.0128182,
    "y": 151.5955157
  },
  {
    "coles": 851,
    "osm": "n2365229637",
    "x": -33.7329862,
    "y": 150.9626977
  },
  {
    "coles": 852,
    "osm": "n4433575404",
    "x": -33.797209,
    "y": 151.1828281
  },
  {
    "coles": 853,
    "osm": "n4236022275",
    "x": -33.8929814,
    "y": 151.250827
  },
  {
    "coles": 854,
    "osm": "w219620947",
    "x": -33.7620085,
    "y": 151.2159368
  },
  {
    "coles": 858,
    "osm": "n2156896056",
    "x": -35.413738,
    "y": 149.128141
  },
  {
    "coles": 859,
    "osm": "n358293199",
    "x": -35.320823,
    "y": 149.1341359
  },
  {
    "coles": 860,
    "osm": "n2053851930",
    "x": -33.7032774,
    "y": 151.1011196
  },
  {
    "coles": 861,
    "osm": "n207331854",
    "x": -33.8747396,
    "y": 151.1069987
  },
  {
    "coles": 862,
    "osm": "n11834093772",
    "x": -33.7698348,
    "y": 150.9059279
  },
  {
    "coles": 864,
    "osm": "n2393649287",
    "x": -32.8360952,
    "y": 151.3543493
  },
  {
    "coles": 865,
    "osm": "n2043378064",
    "x": -33.85721,
    "y": 151.1031659
  },
  {
    "coles": 869,
    "osm": "n1692579894",
    "x": -33.7989033,
    "y": 151.2870032
  },
  {
    "coles": 872,
    "osm": "n3119943853",
    "x": -33.7755644,
    "y": 151.0525627
  },
  {
    "coles": 874,
    "osm": "w403441523",
    "x": -33.7404646,
    "y": 150.7182475
  },
  {
    "coles": 879,
    "osm": "n354865594",
    "x": -32.9242846,
    "y": 151.6232371
  },
  {
    "coles": 880,
    "osm": "n366365343",
    "x": -32.9736798,
    "y": 151.6464633
  },
  {
    "coles": 882,
    "osm": "n11834094256",
    "x": -33.2159664,
    "y": 151.5108061
  },
  {
    "coles": 883,
    "osm": "n1169791685",
    "x": -33.7128398,
    "y": 150.9720455
  },
  {
    "coles": 884,
    "osm": "n570577953",
    "x": -33.6758204,
    "y": 151.3055511
  },
  {
    "coles": 885,
    "osm": "n3118226984",
    "x": -33.4364166,
    "y": 151.3913424
  },
  {
    "coles": 886,
    "osm": "n2200909693",
    "x": -33.7935191,
    "y": 151.2644589
  },
  {
    "coles": 887,
    "osm": "n2227230517",
    "x": -33.8083685,
    "y": 151.0064546
  },
  {
    "coles": 890,
    "osm": "n11834037943",
    "x": -34.371469,
    "y": 150.8976815
  },
  {
    "coles": 893,
    "osm": "n598419217",
    "x": -32.9354467,
    "y": 151.6419859
  },
  {
    "coles": 897,
    "osm": "n1332278555",
    "x": -33.769033,
    "y": 151.2661234
  },
  {
    "coles": 898,
    "osm": "n2736034133",
    "x": -32.762394,
    "y": 151.5921324
  },
  {
    "coles": 899,
    "osm": "n3473228436",
    "x": -33.8794577,
    "y": 151.2368122
  },
  {
    "coles": 901,
    "osm": "n2526168539",
    "x": -32.1988611,
    "y": 152.5187317
  },
  {
    "coles": 903,
    "osm": "n452351363",
    "x": -33.7578989,
    "y": 150.6925299
  },
  {
    "coles": 904,
    "osm": "w763530304",
    "x": -33.3752788,
    "y": 151.4723872
  },
  {
    "coles": 905,
    "osm": "n6439994019",
    "x": -33.4883964,
    "y": 151.3235683
  },
  {
    "coles": 906,
    "osm": "n2179160147",
    "x": -34.0683674,
    "y": 150.8111495
  },
  {
    "coles": 908,
    "osm": "n1928869822",
    "x": -33.9477743,
    "y": 150.8994282
  },
  {
    "coles": 909,
    "osm": "n579697278",
    "x": -33.9443176,
    "y": 151.2238456
  },
  {
    "coles": 911,
    "osm": "n304953129",
    "x": -35.4171599,
    "y": 149.0672353
  },
  {
    "coles": 921,
    "osm": "n2327813591",
    "x": -33.7139254,
    "y": 150.3105023
  },
  {
    "coles": 923,
    "osm": "n922481061",
    "x": -33.980438,
    "y": 151.0760584
  },
  {
    "coles": 924,
    "osm": "n1974473597",
    "x": -33.6921072,
    "y": 150.9258191
  },
  {
    "coles": 925,
    "osm": "n6482336727",
    "x": -33.2834061,
    "y": 151.423245
  },
  {
    "coles": 927,
    "osm": "n11834090034",
    "x": -34.3944416,
    "y": 150.8939052
  },
  {
    "coles": 929,
    "osm": "n3123406337",
    "x": -33.6127001,
    "y": 151.1381686
  },
  {
    "coles": 936,
    "osm": "n11834089618",
    "x": -33.8759889,
    "y": 150.8771575
  },
  {
    "coles": 939,
    "osm": "n1010812558",
    "x": -32.0519636,
    "y": 150.8668648
  },
  {
    "coles": 940,
    "osm": "n11806210384",
    "x": -32.8766678,
    "y": 151.646572
  },
  {
    "coles": 942,
    "osm": "n1081257996",
    "x": -33.9672223,
    "y": 151.1022627
  },
  {
    "coles": 945,
    "osm": "n4726982644",
    "x": -32.566011,
    "y": 151.1644606
  },
  {
    "coles": 946,
    "osm": "n7041170606",
    "x": -32.7161265,
    "y": 151.5288545
  },
  {
    "coles": 950,
    "osm": "n799959491",
    "x": -33.1065497,
    "y": 151.4876568
  },
  {
    "coles": 951,
    "osm": "n849157092",
    "x": -33.7590089,
    "y": 150.9909112
  },
  {
    "coles": 953,
    "osm": "n1927218913",
    "x": -33.9145805,
    "y": 150.9621001
  },
  {
    "coles": 965,
    "osm": "n2565663000",
    "x": -33.8035289,
    "y": 150.9795849
  },
  {
    "coles": 967,
    "osm": "n3952962457",
    "x": -31.9095234,
    "y": 152.4610345
  },
  {
    "coles": 968,
    "osm": "n3889911063",
    "x": -33.8059185,
    "y": 151.0877984
  },
  {
    "coles": 970,
    "osm": "n4144472194",
    "x": -33.7326254,
    "y": 150.7817723
  },
  {
    "coles": 987,
    "osm": "n2546391062",
    "x": -33.8975883,
    "y": 151.2133838
  },
  {
    "coles": 989,
    "osm": "n11806315971",
    "x": -32.7357125,
    "y": 151.9999559
  },
  {
    "coles": 992,
    "osm": "w184910669",
    "x": -33.2642441,
    "y": 151.4647908
  },
  {
    "coles": 993,
    "osm": "n484581893",
    "x": -32.9281344,
    "y": 151.7607959
  },
  {
    "coles": 995,
    "osm": "n11820771234",
    "x": -32.9636404,
    "y": 151.6942736
  },
  {
    "coles": 999,
    "osm": "w964548946",
    "x": -32.8199257,
    "y": 151.4781814
  },
  {
    "coles": 4089,
    "osm": "n9435416846",
    "x": -27.6607215,
    "y": 152.7417849
  },
  {
    "coles": 4090,
    "osm": "n8708033822",
    "x": -27.8093073,
    "y": 152.9496834
  },
  {
    "coles": 4091,
    "osm": "n10221032691",
    "x": -27.0424952,
    "y": 152.9740706
  },
  {
    "coles": 4166,
    "osm": "n9828663372",
    "x": -33.908082,
    "y": 151.1720376
  },
  {
    "coles": 4171,
    "osm": "n2902126168",
    "x": -33.7687743,
    "y": 151.0278074
  },
  {
    "coles": 4177,
    "osm": "n5875641876",
    "x": -33.9963733,
    "y": 150.8669353
  },
  {
    "coles": 4178,
    "osm": "n5449726121",
    "x": -33.0133204,
    "y": 151.6842967
  },
  {
    "coles": 4180,
    "osm": "n6576901203",
    "x": -33.8244009,
    "y": 151.0790184
  },
  {
    "coles": 4334,
    "osm": "n4401054992",
    "x": -27.4692732,
    "y": 153.024566
  },
  {
    "coles": 4368,
    "osm": "n1304245327",
    "x": -28.0374825,
    "y": 153.4265128
  },
  {
    "coles": 4381,
    "osm": "n5068608821",
    "x": -16.8970583,
    "y": 145.698944
  },
  {
    "coles": 4383,
    "osm": "n9729952426",
    "x": -27.8538656,
    "y": 153.316047
  },
  {
    "coles": 4384,
    "osm": "w447968449",
    "x": -28.5456759,
    "y": 150.3043316
  },
  {
    "coles": 4385,
    "osm": "w1007834906",
    "x": -27.4031814,
    "y": 153.0311329
  },
  {
    "coles": 4386,
    "osm": "n6810402627",
    "x": -27.5771931,
    "y": 153.1134471
  },
  {
    "coles": 4388,
    "osm": "n922268821",
    "x": -27.7231149,
    "y": 153.1977339
  },
  {
    "coles": 4389,
    "osm": "n11834321951",
    "x": -21.0982384,
    "y": 149.1855101
  },
  {
    "coles": 4390,
    "osm": "n10221299408",
    "x": -27.9996981,
    "y": 153.3760636
  },
  {
    "coles": 4392,
    "osm": "n8661551887",
    "x": -27.5396031,
    "y": 153.0818117
  },
  {
    "coles": 4401,
    "osm": "n1841274155",
    "x": -28.8597452,
    "y": 153.5609415
  },
  {
    "coles": 4404,
    "osm": "n10221266389",
    "x": -27.0853686,
    "y": 152.9488882
  },
  {
    "coles": 4405,
    "osm": "n2060864004",
    "x": -28.1345264,
    "y": 153.4681847
  },
  {
    "coles": 4406,
    "osm": "n3890023123",
    "x": -23.8699366,
    "y": 151.2393076
  },
  {
    "coles": 4407,
    "osm": "n3853148910",
    "x": -27.6608298,
    "y": 153.1719795
  },
  {
    "coles": 4409,
    "osm": "n3355139144",
    "x": -16.9434486,
    "y": 145.7398508
  },
  {
    "coles": 4410,
    "osm": "n7745905198",
    "x": -17.0196091,
    "y": 145.7275346
  },
  {
    "coles": 4411,
    "osm": "n5245638901",
    "x": -27.3064053,
    "y": 152.991551
  },
  {
    "coles": 4412,
    "osm": "n311429435",
    "x": -27.5507416,
    "y": 152.9391193
  },
  {
    "coles": 4417,
    "osm": "w864996187",
    "x": -27.5646708,
    "y": 151.9137396
  },
  {
    "coles": 4418,
    "osm": "w513062904",
    "x": -27.8674307,
    "y": 153.3500443
  },
  {
    "coles": 4419,
    "osm": "n1631266458",
    "x": -21.0650643,
    "y": 149.1579845
  },
  {
    "coles": 4420,
    "osm": "n1970794784",
    "x": -26.5261101,
    "y": 153.0883421
  },
  {
    "coles": 4421,
    "osm": "n8730239135",
    "x": -27.6254398,
    "y": 152.9681506
  },
  {
    "coles": 4422,
    "osm": "n9591744395",
    "x": -27.2190401,
    "y": 153.0984333
  },
  {
    "coles": 4424,
    "osm": "n10221266391",
    "x": -27.6966491,
    "y": 153.0400987
  },
  {
    "coles": 4425,
    "osm": "n5834618561",
    "x": -21.1585297,
    "y": 149.169382
  },
  {
    "coles": 4430,
    "osm": "n3111899083",
    "x": -27.4088847,
    "y": 152.9802263
  },
  {
    "coles": 4431,
    "osm": "w17503509",
    "x": -27.4243038,
    "y": 152.9995852
  },
  {
    "coles": 4432,
    "osm": "w380212270",
    "x": -27.3422702,
    "y": 153.0427409
  },
  {
    "coles": 4433,
    "osm": "n2376876942",
    "x": -27.5420719,
    "y": 151.9254162
  },
  {
    "coles": 4435,
    "osm": "n3033914408",
    "x": -26.7021401,
    "y": 153.1315499
  },
  {
    "coles": 4436,
    "osm": "r15074857",
    "x": -27.242524,
    "y": 153.0267492
  },
  {
    "coles": 4437,
    "osm": "n8526993574",
    "x": -27.7836841,
    "y": 153.2608894
  },
  {
    "coles": 4438,
    "osm": "w331636781",
    "x": -26.6271237,
    "y": 152.9572396
  },
  {
    "coles": 4440,
    "osm": "n6114240400",
    "x": -26.1883432,
    "y": 152.6614522
  },
  {
    "coles": 4441,
    "osm": "n1292972855",
    "x": -17.523715,
    "y": 146.0286108
  },
  {
    "coles": 4442,
    "osm": "n4891030430",
    "x": -18.6508476,
    "y": 146.153403
  },
  {
    "coles": 4443,
    "osm": "n6244247424",
    "x": -16.933809,
    "y": 145.7537652
  },
  {
    "coles": 4444,
    "osm": "w1006309843",
    "x": -29.7738358,
    "y": 151.1102458
  },
  {
    "coles": 4446,
    "osm": "n3555053978",
    "x": -27.936361,
    "y": 153.3978237
  },
  {
    "coles": 4447,
    "osm": "n1304249101",
    "x": -26.3989995,
    "y": 153.0896952
  },
  {
    "coles": 4449,
    "osm": "n1346651233",
    "x": -27.7184187,
    "y": 153.2024338
  },
  {
    "coles": 4450,
    "osm": "n474996545",
    "x": -27.4218261,
    "y": 153.0351612
  },
  {
    "coles": 4451,
    "osm": "n329990997",
    "x": -27.4453373,
    "y": 153.172004
  },
  {
    "coles": 4452,
    "osm": "n1537317827",
    "x": -27.4582303,
    "y": 151.9586328
  },
  {
    "coles": 4453,
    "osm": "w390178190",
    "x": -27.8321783,
    "y": 153.025977
  },
  {
    "coles": 4455,
    "osm": "n2705104615",
    "x": -23.3564704,
    "y": 150.5225463
  },
  {
    "coles": 4456,
    "osm": "n4191521425",
    "x": -29.6911616,
    "y": 152.9350815
  },
  {
    "coles": 4459,
    "osm": "n3446325069",
    "x": -28.2002215,
    "y": 153.5466587
  },
  {
    "coles": 4460,
    "osm": "n4925840021",
    "x": -28.2973795,
    "y": 153.570242
  },
  {
    "coles": 4461,
    "osm": "w28681037",
    "x": -27.4656677,
    "y": 153.0134557
  },
  {
    "coles": 4462,
    "osm": "n307562186",
    "x": -27.4063642,
    "y": 152.9926384
  },
  {
    "coles": 4464,
    "osm": "n331124797",
    "x": -27.4713952,
    "y": 153.0987059
  },
  {
    "coles": 4467,
    "osm": "w467733976",
    "x": -27.4954832,
    "y": 153.0568741
  },
  {
    "coles": 4471,
    "osm": "n10221266388",
    "x": -27.4442347,
    "y": 152.9920854
  },
  {
    "coles": 4472,
    "osm": "n1959940505",
    "x": -27.6125877,
    "y": 153.1245949
  },
  {
    "coles": 4473,
    "osm": "n937919092",
    "x": -29.4609716,
    "y": 149.8408792
  },
  {
    "coles": 4474,
    "osm": "w620571461",
    "x": -28.1731932,
    "y": 153.5436224
  },
  {
    "coles": 4477,
    "osm": "n2924066154",
    "x": -28.8100357,
    "y": 153.2857574
  },
  {
    "coles": 4478,
    "osm": "n9294815707",
    "x": -26.8034263,
    "y": 153.1249102
  },
  {
    "coles": 4480,
    "osm": "n345097080",
    "x": -27.2978177,
    "y": 152.9765575
  },
  {
    "coles": 4481,
    "osm": "n1635115034",
    "x": -21.1182269,
    "y": 149.1593726
  },
  {
    "coles": 4482,
    "osm": "n4566249089",
    "x": -16.9982993,
    "y": 145.4236335
  },
  {
    "coles": 4483,
    "osm": "n1939135844",
    "x": -27.5592789,
    "y": 152.2769333
  },
  {
    "coles": 4487,
    "osm": "n1965770751",
    "x": -20.7252333,
    "y": 139.4950308
  },
  {
    "coles": 4489,
    "osm": "w1209741792",
    "x": -27.5899381,
    "y": 153.0607713
  },
  {
    "coles": 4490,
    "osm": "n21277708",
    "x": -27.1795492,
    "y": 151.2656074
  },
  {
    "coles": 4491,
    "osm": "n441038760",
    "x": -27.594087,
    "y": 151.9488351
  },
  {
    "coles": 4492,
    "osm": "n5080643676",
    "x": -27.3993875,
    "y": 152.9587219
  },
  {
    "coles": 4494,
    "osm": "n4499863491",
    "x": -19.2977673,
    "y": 146.7605127
  },
  {
    "coles": 4495,
    "osm": "w15773787",
    "x": -27.5386826,
    "y": 152.9828911
  },
  {
    "coles": 4496,
    "osm": "n3998327755",
    "x": -27.6432063,
    "y": 153.1123265
  },
  {
    "coles": 4497,
    "osm": "n3619421894",
    "x": -24.871826,
    "y": 152.3492782
  },
  {
    "coles": 4500,
    "osm": "n2261097030",
    "x": -27.9691258,
    "y": 153.4152827
  },
  {
    "coles": 4501,
    "osm": "n2261089355",
    "x": -27.9979278,
    "y": 153.3383649
  },
  {
    "coles": 4502,
    "osm": "n10221266392",
    "x": -27.6787453,
    "y": 153.1165298
  },
  {
    "coles": 4503,
    "osm": "n2852272012",
    "x": -22.0005114,
    "y": 148.0436676
  },
  {
    "coles": 4504,
    "osm": "n9244690964",
    "x": -27.6051163,
    "y": 152.8683147
  },
  {
    "coles": 4505,
    "osm": "n408409664",
    "x": -28.3282734,
    "y": 153.3962399
  },
  {
    "coles": 4506,
    "osm": "n6023928782",
    "x": -27.4461973,
    "y": 152.9525388
  },
  {
    "coles": 4507,
    "osm": "n5714484694",
    "x": -27.5122039,
    "y": 153.0539042
  },
  {
    "coles": 4508,
    "osm": "w1241623629",
    "x": -27.4848154,
    "y": 152.9927434
  },
  {
    "coles": 4509,
    "osm": "n10105410623",
    "x": -27.525263,
    "y": 153.1918374
  },
  {
    "coles": 4510,
    "osm": "n832516570",
    "x": -19.5717664,
    "y": 147.4049357
  },
  {
    "coles": 4511,
    "osm": "w558465745",
    "x": -27.9891726,
    "y": 152.9997504
  },
  {
    "coles": 4512,
    "osm": "n737246191",
    "x": -27.5090493,
    "y": 153.025925
  },
  {
    "coles": 4513,
    "osm": "n3136331564",
    "x": -25.282761,
    "y": 152.8399474
  },
  {
    "coles": 4514,
    "osm": "n2402939707",
    "x": -27.569411,
    "y": 153.0625208
  },
  {
    "coles": 4515,
    "osm": "w549121760",
    "x": -27.5062151,
    "y": 152.9395463
  },
  {
    "coles": 4516,
    "osm": "n7186894505",
    "x": -27.346853,
    "y": 152.9694848
  },
  {
    "coles": 4518,
    "osm": "n2705143757",
    "x": -23.3762569,
    "y": 150.509323
  },
  {
    "coles": 4519,
    "osm": "n3315837661",
    "x": -27.2264475,
    "y": 153.0874608
  },
  {
    "coles": 4520,
    "osm": "n3610119492",
    "x": -28.0992801,
    "y": 153.4250947
  },
  {
    "coles": 4522,
    "osm": "n5468438953",
    "x": -30.9759124,
    "y": 150.2524674
  },
  {
    "coles": 4523,
    "osm": "n2281525119",
    "x": -26.6558697,
    "y": 153.0889886
  },
  {
    "coles": 4524,
    "osm": "n11834192055",
    "x": -27.3300378,
    "y": 153.02697
  },
  {
    "coles": 4525,
    "osm": "n2484578852",
    "x": -27.6621322,
    "y": 153.0397767
  },
  {
    "coles": 4527,
    "osm": "n3355144064",
    "x": -19.3157909,
    "y": 146.7274754
  },
  {
    "coles": 4528,
    "osm": "n699591219",
    "x": -27.4374089,
    "y": 153.0085337
  },
  {
    "coles": 4529,
    "osm": "w534403706",
    "x": -25.2911638,
    "y": 152.8343678
  },
  {
    "coles": 4530,
    "osm": "n1278107156",
    "x": -27.9136952,
    "y": 153.4002939
  },
  {
    "coles": 4532,
    "osm": "n5152993942",
    "x": -16.8350578,
    "y": 145.6917897
  },
  {
    "coles": 4533,
    "osm": "w549264533",
    "x": -27.652925,
    "y": 152.9185905
  },
  {
    "coles": 4534,
    "osm": "n1284241683",
    "x": -27.5608918,
    "y": 151.9477731
  },
  {
    "coles": 4535,
    "osm": "n8515880306",
    "x": -28.8223778,
    "y": 153.3266223
  },
  {
    "coles": 4536,
    "osm": "n997430185",
    "x": -16.9238828,
    "y": 145.7708538
  },
  {
    "coles": 4537,
    "osm": "n2299022963",
    "x": -27.466922,
    "y": 153.0474782
  },
  {
    "coles": 4539,
    "osm": "n11306738954",
    "x": -27.4564936,
    "y": 153.1558841
  },
  {
    "coles": 4540,
    "osm": "n1363413237",
    "x": -27.5251734,
    "y": 153.2688001
  },
  {
    "coles": 4541,
    "osm": "n3548936706",
    "x": -23.5284165,
    "y": 148.1644824
  },
  {
    "coles": 4545,
    "osm": "n2395901137",
    "x": -27.2430846,
    "y": 153.0189039
  },
  {
    "coles": 4546,
    "osm": "n4746382421",
    "x": -16.4822401,
    "y": 145.462899
  },
  {
    "coles": 4547,
    "osm": "w449021899",
    "x": -27.3856622,
    "y": 153.032591
  },
  {
    "coles": 4550,
    "osm": "n4461196862",
    "x": -26.6792877,
    "y": 153.1169649
  },
  {
    "coles": 4551,
    "osm": "n402306616",
    "x": -29.427775,
    "y": 153.3269682
  },
  {
    "coles": 4553,
    "osm": "n366783365",
    "x": -27.4765102,
    "y": 153.0119529
  },
  {
    "coles": 4554,
    "osm": "n3509261049",
    "x": -27.9990613,
    "y": 153.4277916
  },
  {
    "coles": 4555,
    "osm": "n3807666378",
    "x": -27.9473159,
    "y": 153.3525023
  },
  {
    "coles": 4556,
    "osm": "n7866904059",
    "x": -27.3641926,
    "y": 153.0243883
  },
  {
    "coles": 4557,
    "osm": "n5539319380",
    "x": -27.5555789,
    "y": 152.9223758
  },
  {
    "coles": 4558,
    "osm": "n1737918003",
    "x": -21.1378508,
    "y": 149.1775732
  },
  {
    "coles": 4559,
    "osm": "n2291364973",
    "x": -26.8338234,
    "y": 153.1088748
  },
  {
    "coles": 4560,
    "osm": "n2395659280",
    "x": -27.9935374,
    "y": 153.3319336
  },
  {
    "coles": 4561,
    "osm": "n450676194",
    "x": -27.2720245,
    "y": 153.0168739
  },
  {
    "coles": 4563,
    "osm": "n11834318316",
    "x": -19.3168651,
    "y": 146.7905073
  },
  {
    "coles": 4565,
    "osm": "n9196226962",
    "x": -27.5701855,
    "y": 152.7974739
  },
  {
    "coles": 4566,
    "osm": "w32829722",
    "x": -27.6152541,
    "y": 152.7617007
  },
  {
    "coles": 4567,
    "osm": "w353129942",
    "x": -16.9885675,
    "y": 145.7404173
  },
  {
    "coles": 4568,
    "osm": "w418527092",
    "x": -27.4338665,
    "y": 153.0655323
  },
  {
    "coles": 4569,
    "osm": "n11834282694",
    "x": -19.247344,
    "y": 146.6779256
  },
  {
    "coles": 4570,
    "osm": "n794940028",
    "x": -27.5642181,
    "y": 153.0828557
  },
  {
    "coles": 4571,
    "osm": "n2365234206",
    "x": -27.487294,
    "y": 153.0354953
  },
  {
    "coles": 4572,
    "osm": "n4312164694",
    "x": -28.0482363,
    "y": 153.3542658
  },
  {
    "coles": 4574,
    "osm": "n2149048524",
    "x": -27.5023811,
    "y": 153.1029906
  },
  {
    "coles": 4576,
    "osm": "n2624337588",
    "x": -27.8695825,
    "y": 153.3056754
  },
  {
    "coles": 4577,
    "osm": "n9551714744",
    "x": -28.213663,
    "y": 153.5214311
  },
  {
    "coles": 4578,
    "osm": "n3335308200",
    "x": -27.4650562,
    "y": 153.0791833
  },
  {
    "coles": 4580,
    "osm": "n11834276096",
    "x": -23.9512175,
    "y": 151.3700316
  },
  {
    "coles": 4581,
    "osm": "n1494008798",
    "x": -16.7646243,
    "y": 145.6693493
  },
  {
    "coles": 4582,
    "osm": "n429775973",
    "x": -27.1534755,
    "y": 152.9736982
  },
  {
    "coles": 4583,
    "osm": "n185661985",
    "x": -28.0740437,
    "y": 153.4440994
  },
  {
    "coles": 4584,
    "osm": "n3827955757",
    "x": -27.9257795,
    "y": 153.3368765
  },
  {
    "coles": 4587,
    "osm": "n2968205106",
    "x": -21.1438333,
    "y": 149.1877565
  },
  {
    "coles": 4595,
    "osm": "n4931691822",
    "x": -27.5577584,
    "y": 153.0810816
  },
  {
    "coles": 4596,
    "osm": "n3091796527",
    "x": -27.6080945,
    "y": 152.7575887
  },
  {
    "coles": 4597,
    "osm": "n596833744",
    "x": -28.0801138,
    "y": 153.3649773
  },
  {
    "coles": 4598,
    "osm": "n2591305020",
    "x": -20.2775611,
    "y": 148.7010811
  },
  {
    "coles": 4645,
    "osm": "n3602708199",
    "x": -27.5642359,
    "y": 151.9330916
  },
  {
    "coles": 4647,
    "osm": "w515720020",
    "x": -26.7135916,
    "y": 153.060624
  },
  {
    "coles": 4649,
    "osm": "n10149059216",
    "x": -19.2519668,
    "y": 146.8146356
  },
  {
    "coles": 4651,
    "osm": "n4700169684",
    "x": -28.5242473,
    "y": 153.546475
  },
  {
    "coles": 4652,
    "osm": "n10221266394",
    "x": -27.5704104,
    "y": 152.8773339
  },
  {
    "coles": 4653,
    "osm": "n4148060188",
    "x": -27.9862284,
    "y": 153.4105761
  },
  {
    "coles": 4655,
    "osm": "w581441408",
    "x": -19.2879351,
    "y": 146.7388488
  },
  {
    "coles": 4658,
    "osm": "n3576837205",
    "x": -27.5404538,
    "y": 151.9532491
  },
  {
    "coles": 4659,
    "osm": "n1928762464",
    "x": -25.5374039,
    "y": 152.6975537
  },
  {
    "coles": 4660,
    "osm": "w567779726",
    "x": -27.4990543,
    "y": 152.9733549
  },
  {
    "coles": 4662,
    "osm": "w1223372122",
    "x": -28.2145153,
    "y": 152.0322182
  },
  {
    "coles": 4663,
    "osm": "w1021909302",
    "x": -27.9254608,
    "y": 153.3054075
  },
  {
    "coles": 4666,
    "osm": "n4030878007",
    "x": -27.676934,
    "y": 152.9008469
  },
  {
    "coles": 4667,
    "osm": "n9286572035",
    "x": -27.682658,
    "y": 152.8017541
  },
  {
    "coles": 4669,
    "osm": "n11736398669",
    "x": -27.8497889,
    "y": 153.3025143
  },
  {
    "coles": 4670,
    "osm": "n11377244466",
    "x": -27.3622265,
    "y": 153.0127749
  },
  {
    "coles": 4671,
    "osm": "n5821686988",
    "x": -27.6110134,
    "y": 153.0559086
  },
  {
    "coles": 4674,
    "osm": "n7168568229",
    "x": -26.6142465,
    "y": 153.0821215
  },
  {
    "coles": 4689,
    "osm": "n11832459505",
    "x": -19.2720301,
    "y": 146.7895883
  },
  {
    "coles": 4694,
    "osm": "w1245440680",
    "x": -27.4933963,
    "y": 152.9782482
  },
  {
    "coles": 4782,
    "osm": "n8333254061",
    "x": -27.620959,
    "y": 152.7810681
  },
  {
    "coles": 4783,
    "osm": "n4574411348",
    "x": -27.6447391,
    "y": 152.8685886
  },
  {
    "coles": 4784,
    "osm": "w805125979",
    "x": -27.8024819,
    "y": 153.1018807
  },
  {
    "coles": 4785,
    "osm": "n988538932",
    "x": -35.2202806,
    "y": 149.1031094
  },
  {
    "coles": 4786,
    "osm": "n8285483817",
    "x": -35.391366,
    "y": 149.0855742
  },
  {
    "coles": 4787,
    "osm": "n5656128322",
    "x": -35.278269,
    "y": 149.13382
  },
  {
    "coles": 4788,
    "osm": "n551463636",
    "x": -33.8678925,
    "y": 151.1290494
  },
  {
    "coles": 4789,
    "osm": "w172361382",
    "x": -34.0334089,
    "y": 151.0569428
  },
  {
    "coles": 4790,
    "osm": "n11813796916",
    "x": -32.4095616,
    "y": 115.759651
  },
  {
    "coles": 4796,
    "osm": "n11818520804",
    "x": -32.4708362,
    "y": 115.7595534
  },
  {
    "coles": 4810,
    "osm": "n5541423621",
    "x": -24.8907964,
    "y": 152.3206053
  },
  {
    "coles": 4812,
    "osm": "n4986166743",
    "x": -33.9232794,
    "y": 151.1018842
  },
  {
    "coles": 4813,
    "osm": "n2179162262",
    "x": -34.0757276,
    "y": 150.7981771
  },
  {
    "coles": 4814,
    "osm": "n11337142525",
    "x": -35.2493164,
    "y": 149.1387942
  },
  {
    "coles": 4815,
    "osm": "n11834328360",
    "x": -31.6280801,
    "y": 115.6925736
  },
  {
    "coles": 4824,
    "osm": "n1456898271",
    "x": -31.964452,
    "y": 115.9342256
  },
  {
    "coles": 4835,
    "osm": "n9787115113",
    "x": -27.8132316,
    "y": 153.2934422
  },
  {
    "coles": 4836,
    "osm": "n3744080947",
    "x": -33.6507811,
    "y": 115.3426523
  },
  {
    "coles": 4837,
    "osm": "w1228972108",
    "x": -30.7502302,
    "y": 121.4727987
  },
  {
    "coles": 4838,
    "osm": "n10692456394",
    "x": -32.1002219,
    "y": 115.9656603
  },
  {
    "coles": 4839,
    "osm": "n8901294282",
    "x": -31.8304133,
    "y": 115.9690352
  },
  {
    "coles": 4921,
    "osm": "n11834409050",
    "x": -34.7088169,
    "y": 138.7054412
  },
  {
    "coles": 4924,
    "osm": "n3197999469",
    "x": -34.6866594,
    "y": 138.6888499
  },
  {
    "coles": 4929,
    "osm": "n2179550379",
    "x": -34.7583844,
    "y": 138.5958296
  },
  {
    "coles": 4933,
    "osm": "w259535764",
    "x": -35.1382065,
    "y": 138.4812467
  },
  {
    "coles": 4934,
    "osm": "n2626880955",
    "x": -35.2769647,
    "y": 138.4603118
  },
  {
    "coles": 4940,
    "osm": "n1080147546",
    "x": -35.0640648,
    "y": 138.8601951
  },
  {
    "coles": 4942,
    "osm": "n1285911388",
    "x": -35.0747657,
    "y": 138.5929665
  },
  {
    "coles": 4945,
    "osm": "w25668840",
    "x": -34.9631659,
    "y": 138.5539651
  },
  {
    "coles": 4947,
    "osm": "n5704087569",
    "x": -12.371392,
    "y": 130.8821187
  },
  {
    "coles": 4948,
    "osm": "n11834381816",
    "x": -34.870184,
    "y": 138.6351233
  },
  {
    "coles": 4949,
    "osm": "n890986000",
    "x": -34.8307832,
    "y": 138.6472406
  },
  {
    "coles": 4960,
    "osm": "n4894705318",
    "x": -31.9647824,
    "y": 141.4549711
  },
  {
    "coles": 4961,
    "osm": "w270799025",
    "x": -35.2165477,
    "y": 138.5427243
  },
  {
    "coles": 4964,
    "osm": "n2293314763",
    "x": -34.9238194,
    "y": 138.6027486
  },
  {
    "coles": 4966,
    "osm": "n2258027875",
    "x": -33.0275741,
    "y": 137.5321426
  },
  {
    "coles": 4970,
    "osm": "n4129284397",
    "x": -35.1224014,
    "y": 139.2736509
  },
  {
    "coles": 4971,
    "osm": "n2383968913",
    "x": -34.8698333,
    "y": 138.529625
  },
  {
    "coles": 4972,
    "osm": "n4836645274",
    "x": -34.8651156,
    "y": 138.5809885
  },
  {
    "coles": 4978,
    "osm": "n11341137330",
    "x": -34.6193957,
    "y": 138.7406033
  },
  {
    "coles": 4981,
    "osm": "n6947266286",
    "x": -34.760819,
    "y": 138.6470946
  },
  {
    "coles": 4982,
    "osm": "w39093690",
    "x": -35.0087585,
    "y": 138.5394782
  },
  {
    "coles": 5557,
    "osm": "n5246573649",
    "x": -33.8135343,
    "y": 151.1692596
  },
  {
    "coles": 5587,
    "osm": "n4353558092",
    "x": -33.8392858,
    "y": 151.2089699
  },
  {
    "coles": 5588,
    "osm": "n6149404692",
    "x": -34.0334396,
    "y": 151.0732731
  },
  {
    "coles": 5590,
    "osm": "n6199747170",
    "x": -33.7873563,
    "y": 150.6682155
  },
  {
    "coles": 5597,
    "osm": "n9435115530",
    "x": -29.7395147,
    "y": 151.735611
  },
  {
    "coles": 5598,
    "osm": "w583233831",
    "x": -31.969309,
    "y": 152.5838868
  },
  {
    "coles": 5676,
    "osm": "n11834329696",
    "x": -33.729953,
    "y": 151.1592138
  },
  {
    "coles": 5678,
    "osm": "n2296554735",
    "x": -30.9072967,
    "y": 153.041933
  },
  {
    "coles": 5679,
    "osm": "w343815683",
    "x": -30.2993295,
    "y": 153.1190865
  },
  {
    "coles": 5680,
    "osm": "n2272126829",
    "x": -31.0812475,
    "y": 152.8418439
  },
  {
    "coles": 5681,
    "osm": "n3235972697",
    "x": -30.2066574,
    "y": 153.1492467
  },
  {
    "coles": 5682,
    "osm": "n4312020596",
    "x": -30.3533663,
    "y": 153.0924909
  },
  {
    "coles": 5683,
    "osm": "n17027753",
    "x": -31.4771812,
    "y": 152.9146083
  },
  {
    "coles": 5684,
    "osm": "n986508449",
    "x": -31.4577422,
    "y": 152.8745923
  },
  {
    "coles": 5685,
    "osm": "n17134732",
    "x": -31.6485654,
    "y": 152.796294
  },
  {
    "coles": 5686,
    "osm": "w328300135",
    "x": -31.4339205,
    "y": 152.9073214
  },
  {
    "coles": 5689,
    "osm": "n5021174101",
    "x": -33.4464514,
    "y": 151.3733425
  },
  {
    "coles": 5690,
    "osm": "n1053610605",
    "x": -32.7769316,
    "y": 151.6404035
  },
  {
    "coles": 5691,
    "osm": "w268751894",
    "x": -34.5505941,
    "y": 150.3721646
  },
  {
    "coles": 5692,
    "osm": "n599454874",
    "x": -32.6525353,
    "y": 152.1499594
  },
  {
    "coles": 5693,
    "osm": "n3722202460",
    "x": -29.7064253,
    "y": 152.9385672
  },
  {
    "coles": 5694,
    "osm": "n2264426181",
    "x": -28.8625278,
    "y": 153.0503758
  },
  {
    "coles": 5695,
    "osm": "n2517091831",
    "x": -29.0563849,
    "y": 152.017721
  },
  {
    "coles": 5696,
    "osm": "w693138433",
    "x": -33.3657595,
    "y": 151.4614459
  },
  {
    "coles": 5697,
    "osm": "n3877568614",
    "x": -37.0638556,
    "y": 149.9046139
  },
  {
    "coles": 5698,
    "osm": "w212098616",
    "x": -34.3155352,
    "y": 150.9213275
  },
  {
    "coles": 5714,
    "osm": "n1273724974",
    "x": -32.5544293,
    "y": 148.9430548
  },
  {
    "coles": 5726,
    "osm": "n3084128496",
    "x": -33.326793,
    "y": 151.4289037
  },
  {
    "coles": 5730,
    "osm": "n11834355856",
    "x": -33.4668663,
    "y": 151.3827401
  },
  {
    "coles": 5733,
    "osm": "w294903993",
    "x": -33.520794,
    "y": 151.3175013
  },
  {
    "coles": 5736,
    "osm": "n2143716409",
    "x": -34.1918841,
    "y": 150.982152
  },
  {
    "coles": 5749,
    "osm": "n11834387821",
    "x": -33.83502,
    "y": 148.6889694
  },
  {
    "coles": 5753,
    "osm": "n7730238318",
    "x": -32.5924701,
    "y": 149.5892164
  },
  {
    "coles": 5755,
    "osm": "n6959383790",
    "x": -32.2323141,
    "y": 148.2392582
  },
  {
    "coles": 5757,
    "osm": "w836623647",
    "x": -33.1353193,
    "y": 148.173401
  },
  {
    "coles": 5759,
    "osm": "n11832528792",
    "x": -33.2337086,
    "y": 151.5539219
  },
  {
    "coles": 5769,
    "osm": "n3207035435",
    "x": -34.050462,
    "y": 150.7554712
  },
  {
    "coles": 5770,
    "osm": "n4378114302",
    "x": -33.8679205,
    "y": 150.9230191
  },
  {
    "coles": 5771,
    "osm": "n4000197758",
    "x": -33.1111822,
    "y": 151.5318097
  },
  {
    "coles": 5773,
    "osm": "n28802903",
    "x": -33.7936839,
    "y": 151.1864311
  },
  {
    "coles": 5776,
    "osm": "n3315887722",
    "x": -32.2831154,
    "y": 150.8964941
  },
  {
    "coles": 5777,
    "osm": "n1436336329",
    "x": -33.5817415,
    "y": 150.7207911
  },
  {
    "coles": 5778,
    "osm": "n7164925179",
    "x": -31.8682,
    "y": 152.371
  },
  {
    "coles": 5784,
    "osm": "n5259357720",
    "x": -35.1645617,
    "y": 149.1320065
  },
  {
    "coles": 5791,
    "osm": "n1248155778",
    "x": -33.7781165,
    "y": 151.1209738
  },
  {
    "coles": 5792,
    "osm": "n11005477513",
    "x": -33.9060201,
    "y": 151.0564875
  },
  {
    "coles": 5793,
    "osm": "n9467352817",
    "x": -33.8345794,
    "y": 150.9908519
  },
  {
    "coles": 5796,
    "osm": "n2610157456",
    "x": -31.1046378,
    "y": 150.9190762
  },
  {
    "coles": 5797,
    "osm": "n4405565616",
    "x": -34.5649382,
    "y": 150.8372599
  },
  {
    "coles": 5798,
    "osm": "w1033380861",
    "x": -32.9008806,
    "y": 151.7418622
  },
  {
    "coles": 5800,
    "osm": "n3207040823",
    "x": -34.0391422,
    "y": 150.7374799
  },
  {
    "coles": 5801,
    "osm": "n10014702405",
    "x": -33.811587,
    "y": 151.1069803
  },
  {
    "coles": 5802,
    "osm": "n5512743307",
    "x": -37.837283,
    "y": 144.6912622
  },
  {
    "coles": 5803,
    "osm": "w685844544",
    "x": -19.199794,
    "y": 146.6747754
  },
  {
    "coles": 5804,
    "osm": "n7357800722",
    "x": -37.8339607,
    "y": 144.6510554
  },
  {
    "coles": 5806,
    "osm": "n6418946099",
    "x": -33.9762791,
    "y": 150.8123905
  },
  {
    "coles": 5807,
    "osm": "n611543521",
    "x": -32.9850489,
    "y": 151.6731519
  },
  {
    "coles": 7266,
    "osm": "n5905400958",
    "x": -38.2330593,
    "y": 145.0515325
  },
  {
    "coles": 7500,
    "osm": "n1589051112",
    "x": -42.782713,
    "y": 147.5659321
  },
  {
    "coles": 7501,
    "osm": "n7953132542",
    "x": -38.2277511,
    "y": 144.3399292
  },
  {
    "coles": 7502,
    "osm": "w177261065",
    "x": -41.4056454,
    "y": 147.1320764
  },
  {
    "coles": 7505,
    "osm": "w27615124",
    "x": -42.8960919,
    "y": 147.328783
  },
  {
    "coles": 7523,
    "osm": "n476031171",
    "x": -42.855639,
    "y": 147.305931
  },
  {
    "coles": 7541,
    "osm": "n1050042136",
    "x": -41.0515169,
    "y": 145.9044973
  },
  {
    "coles": 7543,
    "osm": "w966014172",
    "x": -32.6300686,
    "y": 115.6308666
  },
  {
    "coles": 7545,
    "osm": "w1156834170",
    "x": -32.0637463,
    "y": 115.7817919
  },
  {
    "coles": 7546,
    "osm": "n7690432997",
    "x": -37.8196048,
    "y": 145.1203412
  },
  {
    "coles": 7547,
    "osm": "n9901285170",
    "x": -42.888138,
    "y": 147.427601
  },
  {
    "coles": 7549,
    "osm": "n10877242451",
    "x": -33.6581552,
    "y": 150.8802688
  },
  {
    "coles": 7554,
    "osm": "n1739341581",
    "x": -33.3853616,
    "y": 151.3677247
  },
  {
    "coles": 7555,
    "osm": "n2468391940",
    "x": -32.7398764,
    "y": 151.8652867
  },
  {
    "coles": 7556,
    "osm": "n11827017634",
    "x": -33.7511556,
    "y": 150.6937139
  },
  {
    "coles": 7558,
    "osm": "n5872504538",
    "x": -33.9532004,
    "y": 151.014525
  },
  {
    "coles": 7559,
    "osm": "n10698432081",
    "x": -27.1935283,
    "y": 153.0289754
  },
  {
    "coles": 7562,
    "osm": "n527560529",
    "x": -41.4293044,
    "y": 147.1483932
  },
  {
    "coles": 7565,
    "osm": "n6250572091",
    "x": -32.7365206,
    "y": 152.1075174
  },
  {
    "coles": 7569,
    "osm": "n3390252746",
    "x": -33.9048457,
    "y": 151.2131902
  },
  {
    "coles": 7572,
    "osm": "n9295225313",
    "x": -33.7057021,
    "y": 150.8761413
  },
  {
    "coles": 7574,
    "osm": "n11413306247",
    "x": -37.8784912,
    "y": 145.0923339
  },
  {
    "coles": 7577,
    "osm": "n6814009002",
    "x": -33.823142,
    "y": 151.2011466
  },
  {
    "coles": 7579,
    "osm": "n9404528718",
    "x": -34.7455464,
    "y": 146.5536468
  },
  {
    "coles": 7587,
    "osm": "n3235709832",
    "x": -34.424162,
    "y": 150.8924763
  },
  {
    "coles": 7591,
    "osm": "n4733192148",
    "x": -35.0703788,
    "y": 150.6744601
  },
  {
    "coles": 7596,
    "osm": "n9467594908",
    "x": -33.8593696,
    "y": 150.8975809
  },
  {
    "coles": 7600,
    "osm": "n1392002621",
    "x": -37.7417028,
    "y": 142.0249015
  },
  {
    "coles": 7601,
    "osm": "w163700279",
    "x": -38.0849951,
    "y": 145.2928351
  },
  {
    "coles": 7602,
    "osm": "n3161934861",
    "x": -42.8653782,
    "y": 147.368848
  },
  {
    "coles": 7606,
    "osm": "n631989371",
    "x": -41.157542,
    "y": 146.1703265
  },
  {
    "coles": 7611,
    "osm": "n3624177341",
    "x": -37.5923694,
    "y": 144.9150075
  },
  {
    "coles": 7612,
    "osm": "n1278126817",
    "x": -37.7518375,
    "y": 144.7756103
  },
  {
    "coles": 7616,
    "osm": "w780427028",
    "x": -37.3582279,
    "y": 144.5255766
  },
  {
    "coles": 7618,
    "osm": "n2708666931",
    "x": -36.8108831,
    "y": 144.2435224
  },
  {
    "coles": 7619,
    "osm": "n4875093169",
    "x": -37.7017311,
    "y": 144.574255
  },
  {
    "coles": 7620,
    "osm": "n8985718735",
    "x": -38.1740625,
    "y": 144.5729134
  },
  {
    "coles": 7621,
    "osm": "n602318240",
    "x": -41.1766608,
    "y": 146.3551924
  },
  {
    "coles": 7623,
    "osm": "w326150517",
    "x": -38.0628628,
    "y": 145.5067669
  },
  {
    "coles": 7629,
    "osm": "n874976366",
    "x": -42.9744595,
    "y": 147.3112534
  },
  {
    "coles": 7645,
    "osm": "w804041931",
    "x": -42.8319921,
    "y": 147.2745657
  },
  {
    "coles": 7646,
    "osm": "n392159314",
    "x": -41.4676376,
    "y": 147.1586004
  },
  {
    "coles": 7647,
    "osm": "n1055752546",
    "x": -42.7347376,
    "y": 147.2431521
  },
  {
    "coles": 7656,
    "osm": "w194224211",
    "x": -41.441888,
    "y": 147.1400458
  },
  {
    "coles": 7658,
    "osm": "w194224224",
    "x": -41.4448686,
    "y": 147.138628
  },
  {
    "coles": 7659,
    "osm": "n493904424",
    "x": -41.4411311,
    "y": 147.1609718
  },
  {
    "coles": 7661,
    "osm": "n11145219512",
    "x": -33.8236372,
    "y": 151.1950876
  },
  {
    "coles": 7662,
    "osm": "n2624345614",
    "x": -33.9163633,
    "y": 151.0373091
  },
  {
    "coles": 7663,
    "osm": "n6779489132",
    "x": -33.8176983,
    "y": 150.9999003
  },
  {
    "coles": 7664,
    "osm": "n11834432297",
    "x": -37.7752157,
    "y": 144.8866386
  },
  {
    "coles": 7669,
    "osm": "n11834437309",
    "x": -37.5733957,
    "y": 144.8994405
  },
  {
    "coles": 7689,
    "osm": "n8745976197",
    "x": -33.8704197,
    "y": 151.2065633
  },
  {
    "coles": 7690,
    "osm": "n8508535994",
    "x": -38.1518662,
    "y": 145.1670108
  },
  {
    "coles": 7691,
    "osm": "n5905408641",
    "x": -37.7781318,
    "y": 144.8514648
  },
  {
    "coles": 7693,
    "osm": "w71071371",
    "x": -38.3316698,
    "y": 144.3198144
  },
  {
    "coles": 7695,
    "osm": "n4200853794",
    "x": -38.0321022,
    "y": 145.3450266
  },
  {
    "coles": 7697,
    "osm": "n480460754",
    "x": -38.0686164,
    "y": 145.3007558
  },
  {
    "coles": 7698,
    "osm": "n5230328952",
    "x": -36.1202037,
    "y": 146.8888404
  },
  {
    "coles": 7702,
    "osm": "n7922125709",
    "x": -32.6698376,
    "y": 151.3499958
  },
  {
    "coles": 7703,
    "osm": "n2268930955",
    "x": -37.638387,
    "y": 144.9323564
  },
  {
    "coles": 7704,
    "osm": "n8261144499",
    "x": -33.7933008,
    "y": 151.1341846
  },
  {
    "coles": 7705,
    "osm": "w437901776",
    "x": -37.6296479,
    "y": 145.0794343
  },
  {
    "coles": 7707,
    "osm": "n9584001094",
    "x": -37.8302752,
    "y": 140.7828991
  },
  {
    "coles": 7708,
    "osm": "n11806433551",
    "x": -33.8929981,
    "y": 151.0616442
  },
  {
    "coles": 7710,
    "osm": "n9279500398",
    "x": -33.6957965,
    "y": 150.8201378
  },
  {
    "coles": 7714,
    "osm": "w220228589",
    "x": -37.5997372,
    "y": 143.839856
  },
  {
    "coles": 7716,
    "osm": "w190526844",
    "x": -38.004827,
    "y": 145.2664991
  },
  {
    "coles": 7717,
    "osm": "n5009375193",
    "x": -37.8596976,
    "y": 144.6665023
  },
  {
    "coles": 7718,
    "osm": "n832563928",
    "x": -37.8815939,
    "y": 144.7032684
  },
  {
    "coles": 7719,
    "osm": "n9805211549",
    "x": -37.8173906,
    "y": 144.9988683
  },
  {
    "coles": 7721,
    "osm": "n10743106111",
    "x": -37.8112818,
    "y": 145.1535054
  },
  {
    "coles": 7724,
    "osm": "n10223008755",
    "x": -37.8760273,
    "y": 145.0376175
  },
  {
    "coles": 7730,
    "osm": "w524354199",
    "x": -38.3817118,
    "y": 142.4838505
  },
  {
    "coles": 7731,
    "osm": "n768257901",
    "x": -38.0140108,
    "y": 145.3222251
  },
  {
    "coles": 7733,
    "osm": "n10212909074",
    "x": -38.1497807,
    "y": 145.2897666
  },
  {
    "coles": 7735,
    "osm": "n465186430",
    "x": -37.7869266,
    "y": 145.1257942
  },
  {
    "coles": 7739,
    "osm": "w111679185",
    "x": -37.7391583,
    "y": 145.0282899
  },
  {
    "coles": 7748,
    "osm": "n11586763975",
    "x": -38.0949019,
    "y": 145.3623668
  },
  {
    "coles": 7749,
    "osm": "n1791659674",
    "x": -36.4082906,
    "y": 145.3910392
  },
  {
    "coles": 7757,
    "osm": "n6917971490",
    "x": -37.8848116,
    "y": 145.0068377
  },
  {
    "coles": 7758,
    "osm": "n4446892792",
    "x": -38.1191101,
    "y": 145.3205054
  },
  {
    "coles": 7761,
    "osm": "n8892284913",
    "x": -37.7140271,
    "y": 144.6022542
  },
  {
    "coles": 7762,
    "osm": "n6924390121",
    "x": -37.6000034,
    "y": 145.0952382
  },
  {
    "coles": 7766,
    "osm": "w523105425",
    "x": -37.8038373,
    "y": 145.0376993
  },
  {
    "coles": 7770,
    "osm": "n3942998909",
    "x": -37.8013978,
    "y": 144.897529
  },
  {
    "coles": 7771,
    "osm": "n4709207011",
    "x": -37.6216014,
    "y": 145.0064337
  },
  {
    "coles": 7774,
    "osm": "w329099952",
    "x": -37.8168699,
    "y": 144.8810707
  },
  {
    "coles": 7775,
    "osm": "n5144855747",
    "x": -38.3410762,
    "y": 143.5940289
  },
  {
    "coles": 7776,
    "osm": "n3370051198",
    "x": -38.0235593,
    "y": 144.410367
  },
  {
    "coles": 7777,
    "osm": "n8940011710",
    "x": -37.9028636,
    "y": 144.6590679
  },
  {
    "coles": 7778,
    "osm": "n563701491",
    "x": -37.4133779,
    "y": 144.9783977
  },
  {
    "coles": 7780,
    "osm": "n1734717976",
    "x": -37.0234963,
    "y": 145.1337096
  },
  {
    "coles": 7781,
    "osm": "n1927286976",
    "x": -38.1465194,
    "y": 144.3634189
  },
  {
    "coles": 7782,
    "osm": "n552752115",
    "x": -37.7971249,
    "y": 145.2569815
  },
  {
    "coles": 7784,
    "osm": "n669188509",
    "x": -37.7691345,
    "y": 145.0013383
  },
  {
    "coles": 7786,
    "osm": "n1282664873",
    "x": -37.6749254,
    "y": 145.0357476
  },
  {
    "coles": 7787,
    "osm": "w391365574",
    "x": -37.9453066,
    "y": 145.0217912
  },
  {
    "coles": 7789,
    "osm": "w236242345",
    "x": -37.7437412,
    "y": 144.9106915
  },
  {
    "coles": 7793,
    "osm": "n1793129351",
    "x": -37.7592178,
    "y": 144.7534185
  },
  {
    "coles": 7794,
    "osm": "w33840185",
    "x": -37.7724084,
    "y": 144.9488152
  },
  {
    "coles": 7795,
    "osm": "n508030779",
    "x": -37.7936568,
    "y": 144.8603614
  },
  {
    "coles": 7796,
    "osm": "w266677771",
    "x": -38.1736001,
    "y": 144.3430639
  },
  {
    "coles": 7797,
    "osm": "n3676221315",
    "x": -37.8038542,
    "y": 145.1021788
  },
  {
    "coles": 7798,
    "osm": "w127972375",
    "x": -37.5613787,
    "y": 143.8685099
  },
  {
    "coles": 7799,
    "osm": "n2943276352",
    "x": -37.7976134,
    "y": 144.8061424
  },
  {
    "coles": 7801,
    "osm": "w612495369",
    "x": -37.8334247,
    "y": 145.0773388
  },
  {
    "coles": 7802,
    "osm": "w1149050187",
    "x": -37.8241567,
    "y": 145.0972292
  },
  {
    "coles": 7804,
    "osm": "n990857152",
    "x": -37.8425504,
    "y": 145.2667021
  },
  {
    "coles": 7808,
    "osm": "n1237251095",
    "x": -37.7149789,
    "y": 144.88468
  },
  {
    "coles": 7810,
    "osm": "w1234494593",
    "x": -38.1999126,
    "y": 144.3167547
  },
  {
    "coles": 7812,
    "osm": "n3398088890",
    "x": -37.7254998,
    "y": 145.0281053
  },
  {
    "coles": 7819,
    "osm": "n3270433150",
    "x": -37.9060865,
    "y": 145.0051856
  },
  {
    "coles": 7823,
    "osm": "n8093158408",
    "x": -33.970356,
    "y": 150.8583333
  },
  {
    "coles": 7824,
    "osm": "n7602483886",
    "x": -19.3150136,
    "y": 146.8159829
  },
  {
    "coles": 7831,
    "osm": "w582717934",
    "x": -36.5497326,
    "y": 145.9858493
  },
  {
    "coles": 7832,
    "osm": "w714958375",
    "x": -35.5348511,
    "y": 138.637087
  },
  {
    "coles": 7834,
    "osm": "n9322990502",
    "x": -28.1223399,
    "y": 153.4726944
  },
  {
    "coles": 7835,
    "osm": "w1126675745",
    "x": -26.6627624,
    "y": 153.0503334
  },
  {
    "coles": 7836,
    "osm": "n6907985653",
    "x": -26.7402487,
    "y": 153.1158584
  },
  {
    "coles": 7838,
    "osm": "w109684503",
    "x": -36.7576168,
    "y": 144.2962722
  },
  {
    "coles": 7840,
    "osm": "n9287409313",
    "x": -34.2108266,
    "y": 142.1396072
  },
  {
    "coles": 7841,
    "osm": "n4793241132",
    "x": -37.711603,
    "y": 144.7415653
  },
  {
    "coles": 7842,
    "osm": "n3800095557",
    "x": -37.803803,
    "y": 144.983619
  },
  {
    "coles": 7843,
    "osm": "n8310223092",
    "x": -37.5365138,
    "y": 144.9212675
  },
  {
    "coles": 7844,
    "osm": "n8573203227",
    "x": -37.7227961,
    "y": 144.6701494
  },
  {
    "coles": 7868,
    "osm": "w255432027",
    "x": -38.4527005,
    "y": 145.238444
  },
  {
    "coles": 7881,
    "osm": "n3214773256",
    "x": -37.8117934,
    "y": 145.2299716
  },
  {
    "coles": 7894,
    "osm": "w333778606",
    "x": -36.5614438,
    "y": 146.7264127
  },
  {
    "coles": 7917,
    "osm": "w93700905",
    "x": -38.1389962,
    "y": 144.3374854
  },
  {
    "coles": 7918,
    "osm": "n1027335272",
    "x": -38.1071313,
    "y": 145.2818531
  },
  {
    "coles": 7919,
    "osm": "n3613961947",
    "x": -37.7315658,
    "y": 144.9503452
  },
  {
    "coles": 7935,
    "osm": "n365210758",
    "x": -38.115432,
    "y": 145.1930495
  },
  {
    "coles": 7992,
    "osm": "n1668375381",
    "x": -37.0487286,
    "y": 143.7414417
  },
  {
    "coles": 7994,
    "osm": "n1937616038",
    "x": -37.7824892,
    "y": 144.9148871
  },
  {
    "coles": 7997,
    "osm": "n7342542045",
    "x": -37.7721229,
    "y": 144.9784681
  },
  {
    "coles": 7998,
    "osm": "n441991395",
    "x": -37.8254909,
    "y": 144.9947938
  },
  {
    "coles": 8712,
    "osm": "n2055160336",
    "x": -27.4044982,
    "y": 152.931327
  },
  {
    "coles": 8714,
    "osm": "w527463968",
    "x": -27.5334256,
    "y": 152.948239
  },
  {
    "coles": 8715,
    "osm": "w391496028",
    "x": -27.2409825,
    "y": 152.9939351
  },
  {
    "coles": 8721,
    "osm": "n7634594288",
    "x": -27.104259,
    "y": 152.9497679
  },
  {
    "coles": 8729,
    "osm": "n8041436430",
    "x": -27.588166,
    "y": 153.2802691
  },
  {
    "coles": 8731,
    "osm": "n3085468932",
    "x": -23.1290764,
    "y": 150.7408955
  },
  {
    "coles": 8736,
    "osm": "n11834315437",
    "x": -27.7631124,
    "y": 153.2449637
  },
  {
    "coles": 8737,
    "osm": "n978444451",
    "x": -27.8993762,
    "y": 153.2843243
  },
  {
    "coles": 8739,
    "osm": "n3841683431",
    "x": -28.0089478,
    "y": 153.3926149
  },
  {
    "coles": 8741,
    "osm": "n3354856691",
    "x": -28.0459549,
    "y": 153.4081833
  },
  {
    "coles": 8750,
    "osm": "n5287029468",
    "x": -28.8435498,
    "y": 153.4400563
  },
  {
    "coles": 8757,
    "osm": "n4458516913",
    "x": -27.6930781,
    "y": 153.1350038
  },
  {
    "coles": 8758,
    "osm": "n4785452922",
    "x": -26.4966674,
    "y": 153.0799654
  },
  {
    "coles": 8760,
    "osm": "w568899455",
    "x": -30.5128189,
    "y": 151.668922
  },
  {
    "coles": 8761,
    "osm": "n388454248",
    "x": -31.0926416,
    "y": 150.9323119
  },
  {
    "coles": 8769,
    "osm": "n1788067732",
    "x": -30.3238921,
    "y": 149.7827512
  },
  {
    "coles": 8770,
    "osm": "w980904817",
    "x": -31.0770907,
    "y": 150.9180602
  },
  {
    "coles": 8786,
    "osm": "n1766341028",
    "x": -38.0185007,
    "y": 145.306709
  },
  {
    "coles": 8787,
    "osm": "n2108372908",
    "x": -38.6037001,
    "y": 145.5864483
  }
]
